{"companySeoName":"cognizant-technology-solutions","companyName":"Cognizant Technology Solutions","location":"Teaneck, New Jersey, United States","imageExist":"True","socialUrlMap":{"linkedin":"https://www.linkedin.com/company/cognizant-technology-solutions","facebook":"https://www.facebook.com/Cognizant","twiter":"https://twitter.com/cognizant"},"reviewQuestionAnswesSection":[{"sectionName":"Salary","sectionNameHi":null,"reviewQuestionAnswesViews":[{"QuestionText":"Is the salary as per market standard?","QuestionTextHi":null,"AnswerText":null,"AnswerTextHi":null,"totalAnswerCount":"1351","answersView":[{"AnswerText":"Yes","AnswerTextHi":"हाँ","AnswerCount":"644"},{"AnswerText":"No","AnswerTextHi":"नहीं","AnswerCount":"707"}]},{"QuestionText":"Tell us about your last increment","QuestionTextHi":null,"AnswerText":null,"AnswerTextHi":null,"totalAnswerCount":"1337","answersView":[{"AnswerText":"Less than 10%","AnswerTextHi":"10 से कम%","AnswerCount":"714"},{"AnswerText":"10-15%","AnswerTextHi":"10-15%","AnswerCount":"369"},{"AnswerText":"15-20%","AnswerTextHi":"15-20%","AnswerCount":"111"},{"AnswerText":"Not Eligible","AnswerTextHi":"पात्र नहीं है","AnswerCount":"143"}]}]},{"sectionName":"Work life balance","sectionNameHi":null,"reviewQuestionAnswesViews":[{"QuestionText":"How many hours you normally work in a day?","QuestionTextHi":null,"AnswerText":null,"AnswerTextHi":null,"totalAnswerCount":"35","answersView":[{"AnswerText":"5-6 Hours","AnswerTextHi":"5-6 घंटे","AnswerCount":"11"},{"AnswerText":"8-10 Hours","AnswerTextHi":"8-10 घंटे","AnswerCount":"16"},{"AnswerText":"10+ Hours","AnswerTextHi":"10+ घंटे","AnswerCount":"8"}]},{"QuestionText":"Does Cognizant Technology Solutions have a flexible working hours policy?","QuestionTextHi":null,"AnswerText":null,"AnswerTextHi":null,"totalAnswerCount":"35","answersView":[{"AnswerText":"Yes","AnswerTextHi":"हाँ","AnswerCount":"16"},{"AnswerText":"No","AnswerTextHi":"नहीं","AnswerCount":"5"},{"AnswerText":"Case to case basis","AnswerTextHi":"केस टू केस आधार","AnswerCount":"14"}]}]},{"sectionName":"Company culture","sectionNameHi":null,"reviewQuestionAnswesViews":[{"QuestionText":"How smart are your colleagues?","QuestionTextHi":null,"AnswerText":null,"AnswerTextHi":null,"totalAnswerCount":"1405","answersView":[{"AnswerText":"Extremely smart","AnswerTextHi":"बेहद होशियार","AnswerCount":"434"},{"AnswerText":"Average","AnswerTextHi":"औसत","AnswerCount":"838"},{"AnswerText":"Below average","AnswerTextHi":"औसत से कम","AnswerCount":"133"}]},{"QuestionText":"How punctual are your co-workers?","QuestionTextHi":null,"AnswerText":null,"AnswerTextHi":null,"totalAnswerCount":"1407","answersView":[{"AnswerText":"Always on time","AnswerTextHi":"हमेशा समय पर","AnswerCount":"366"},{"AnswerText":"Most of time","AnswerTextHi":"अधिकांश समय","AnswerCount":"840"},{"AnswerText":"Seldom on time","AnswerTextHi":"समय पर शायद ही कभी","AnswerCount":"201"}]},{"QuestionText":"How often do you have parties/offsites?","QuestionTextHi":null,"AnswerText":null,"AnswerTextHi":null,"totalAnswerCount":"1415","answersView":[{"AnswerText":"Weekly","AnswerTextHi":"साप्ताहिक","AnswerCount":"35"},{"AnswerText":"Monthly","AnswerTextHi":"महीने के","AnswerCount":"116"},{"AnswerText":"Quarterly","AnswerTextHi":"त्रैमासिक","AnswerCount":"411"},{"AnswerText":"Yearly","AnswerTextHi":"सालाना","AnswerCount":"637"},{"AnswerText":"Managment doesn't believe in it","AnswerTextHi":"प्रबंधन इस पर विश्वास नहीं करता है","AnswerCount":"216"}]}]},{"sectionName":"Career growth","sectionNameHi":null,"reviewQuestionAnswesViews":[{"QuestionText":"How often do employees get promotions?","QuestionTextHi":null,"AnswerText":null,"AnswerTextHi":null,"totalAnswerCount":"1405","answersView":[{"AnswerText":"Less than 1 year","AnswerTextHi":"एक वर्ष से कम","AnswerCount":"55"},{"AnswerText":"1-2 Years","AnswerTextHi":"1-2 साल","AnswerCount":"311"},{"AnswerText":"2-3 Years","AnswerTextHi":"2-3 साल","AnswerCount":"475"},{"AnswerText":"3+ Years","AnswerTextHi":"3+ साल","AnswerCount":"564"}]},{"QuestionText":"How many trainings do you attend every year?","QuestionTextHi":null,"AnswerText":null,"AnswerTextHi":null,"totalAnswerCount":"1403","answersView":[{"AnswerText":"More than 6 times in a year","AnswerTextHi":"एक वर्ष में 6 बार से अधिक","AnswerCount":"248"},{"AnswerText":"3-5 times in a year","AnswerTextHi":"एक वर्ष में 3-5 बार","AnswerCount":"372"},{"AnswerText":"1-2 times in a year","AnswerTextHi":"एक वर्ष में 1-2 बार","AnswerCount":"534"},{"AnswerText":"No such programs","AnswerTextHi":"ऐसे कोई कार्यक्रम नहीं","AnswerCount":"249"}]}]}],"widgets":{"facebookFeedUrl":"https://www.facebook.com/cognizant","twitterFeedUrl":"https://twitter.com/Cognizant","twitterWidgetId":"690073801003028480","stockTickerCode":""},"companyVarient":["cognizant technology solutions india","cognizant technology solutions bangalore","cognizant technology solutions ind pvt ltd","cognizant techonology solutions","cognizant technology solutions cts","cognizant technology solution india pvt ltd","cognizant technology solutions pune","cognizant technology solutions hyderabad","cognizant technololgy solutions","cts banglore","cognizant cts","cts","cognizant india private limited","cognizant technology solutions mumbai","cognizant technologies","cognizant technologies solutions","cognizant","cognizant technology soultions","cognizant technology services","cognizant technology solutions","cts pune","cognizant technology solutins","cts chennai","cognizant technology solns","cognizant technology and solutions","cognizant technology solutions india pvt ltd","cognizant technology solution pvt ltd","cognizant technologies solutions india pvt ltd","cognizant technolgy solutions","cognizant technology solutions corporation","cognizant technology solutions pvt ltd","cognizant tech solutions","cognizant tecnology solutions","cognizant technological solutions","cognizant technology solutions india private limited","cognizant technology solutions kolkata","cognizant technologies solution","cognizant technology solutions india ltd","cts hyderabad","cognizant techonology solution","cognizant technology solution","cts corporation","cognizant technology","cognizant globle services pvt ltd","cognizant business consulting","cognizant technologies solutions pvt ltd","cognizant technology solutions india private ltd","cognizant technology solutions ltd","coginizant technology solutions","cts pvt ltd","cognizant technology solutions india limited","cognizant technology solutins india pvt ltd","cognizant technology solutions limited","cognizant technology solutions private limited","cogzinant","cognizant technology solutions chennai","cognizant techology solutions","cognizant technology solutions coimbatore","cognizant technology solutions india pvt limited","cognizant technical solutions","cognizant technology solution p ltd","cognizant india pvt ltd"],"individualRatings":{"overAllRating":3.46,"salary":3.38,"workLife":3.46,"culture":3.66,"growth":3.35},"counts":{"mixedFeelCount":1029,"notRecommendCount":645,"recommendCount":856},"companySalary":{"totalResults":353,"results":[{"salaryTitle":"Software Developer/ Programmer","salaryTitleHi":null,"employeeDesignation":"Software Developer/ Programmer","employeeDesignationHi":null,"cmpRating":3.46,"noRatedBy":11919,"salaryMin":274017,"salaryMax":858940,"salaryMean":484980},{"salaryTitle":"Team Lead/ Tech Lead","salaryTitleHi":null,"employeeDesignation":"Team Lead/ Tech Lead","employeeDesignationHi":null,"cmpRating":3.46,"noRatedBy":3026,"salaryMin":349637,"salaryMax":1313531,"salaryMean":751130},{"salaryTitle":"Software Testing Engineer/ Test Automation Engineer","salaryTitleHi":null,"employeeDesignation":"Software Testing Engineer/ Test Automation Engineer","employeeDesignationHi":null,"cmpRating":3.46,"noRatedBy":2516,"salaryMin":242627,"salaryMax":812064,"salaryMean":474197},{"salaryTitle":"Project Leader/ Project Manager","salaryTitleHi":null,"employeeDesignation":"Project Leader/ Project Manager","employeeDesignationHi":null,"cmpRating":3.46,"noRatedBy":2079,"salaryMin":481904,"salaryMax":1794761,"salaryMean":1078953},{"salaryTitle":"Data Warehouse Developer","salaryTitleHi":null,"employeeDesignation":"Data Warehouse Developer","employeeDesignationHi":null,"cmpRating":3.46,"noRatedBy":1854,"salaryMin":293021,"salaryMax":948445,"salaryMean":530531},{"salaryTitle":"Fresher","salaryTitleHi":null,"employeeDesignation":"Fresher","employeeDesignationHi":null,"cmpRating":3.46,"noRatedBy":1669,"salaryMin":190801,"salaryMax":604867,"salaryMean":361219},{"salaryTitle":"Software Quality Assurance Analyst","salaryTitleHi":null,"employeeDesignation":"Software Quality Assurance Analyst","employeeDesignationHi":null,"cmpRating":3.46,"noRatedBy":1632,"salaryMin":251893,"salaryMax":803290,"salaryMean":470259},{"salaryTitle":"System Administrator","salaryTitleHi":null,"employeeDesignation":"System Administrator","employeeDesignationHi":null,"cmpRating":3.46,"noRatedBy":1329,"salaryMin":213107,"salaryMax":1020154,"salaryMean":531178},{"salaryTitle":"Other IT Software - Others","salaryTitleHi":null,"employeeDesignation":"Other IT Software - Others","employeeDesignationHi":null,"cmpRating":3.46,"noRatedBy":1120,"salaryMin":203369,"salaryMax":900708,"salaryMean":494982},{"salaryTitle":"Lead Testing Engineer","salaryTitleHi":null,"employeeDesignation":"Lead Testing Engineer","employeeDesignationHi":null,"cmpRating":3.46,"noRatedBy":1064,"salaryMin":310564,"salaryMax":1167328,"salaryMean":673868},{"salaryTitle":"Software Quality Assurance Engineer","salaryTitleHi":null,"employeeDesignation":"Software Quality Assurance Engineer","employeeDesignationHi":null,"cmpRating":3.46,"noRatedBy":977,"salaryMin":267445,"salaryMax":920915,"salaryMean":520313},{"salaryTitle":"Other IT Software - QA and Testing","salaryTitleHi":null,"employeeDesignation":"Other IT Software - QA and Testing","employeeDesignationHi":null,"cmpRating":3.46,"noRatedBy":937,"salaryMin":213736,"salaryMax":947005,"salaryMean":489307},{"salaryTitle":"Business Analyst","salaryTitleHi":null,"employeeDesignation":"Business Analyst","employeeDesignationHi":null,"cmpRating":3.46,"noRatedBy":897,"salaryMin":299551,"salaryMax":1582229,"salaryMean":816599},{"salaryTitle":"Other IT Software - Application Programming","salaryTitleHi":null,"employeeDesignation":"Other IT Software - Application Programming","employeeDesignationHi":null,"cmpRating":3.46,"noRatedBy":881,"salaryMin":263268,"salaryMax":768125,"salaryMean":449457},{"salaryTitle":"Database Analyst/ Programmer","salaryTitleHi":null,"employeeDesignation":"Database Analyst/ Programmer","employeeDesignationHi":null,"cmpRating":3.46,"noRatedBy":788,"salaryMin":273266,"salaryMax":854807,"salaryMean":481891},{"salaryTitle":"Database Administrator (DBA)","salaryTitleHi":null,"employeeDesignation":"Database Administrator (DBA)","employeeDesignationHi":null,"cmpRating":3.46,"noRatedBy":758,"salaryMin":281466,"salaryMax":1297106,"salaryMean":634377},{"salaryTitle":"Technical Support Engineer","salaryTitleHi":null,"employeeDesignation":"Technical Support Engineer","employeeDesignationHi":null,"cmpRating":3.46,"noRatedBy":676,"salaryMin":225698,"salaryMax":964340,"salaryMean":499125},{"salaryTitle":"Other IT Software - DataBase, Datawarehousing","salaryTitleHi":null,"employeeDesignation":"Other IT Software - DataBase, Datawarehousing","employeeDesignationHi":null,"cmpRating":3.46,"noRatedBy":626,"salaryMin":301712,"salaryMax":1090909,"salaryMean":588316},{"salaryTitle":"Other IT Software - Operations/ Support Services","salaryTitleHi":null,"employeeDesignation":"Other IT Software - Operations/ Support Services","employeeDesignationHi":null,"cmpRating":3.46,"noRatedBy":614,"salaryMin":241352,"salaryMax":939204,"salaryMean":507821},{"salaryTitle":"Accountant/ Accounts Executive","salaryTitleHi":null,"employeeDesignation":"Accountant/ Accounts Executive","employeeDesignationHi":null,"cmpRating":3.46,"noRatedBy":539,"salaryMin":178537,"salaryMax":581294,"salaryMean":329828},{"salaryTitle":"Management Trainee/ Trainee","salaryTitleHi":null,"employeeDesignation":"Management Trainee/ Trainee","employeeDesignationHi":null,"cmpRating":3.46,"noRatedBy":499,"salaryMin":189561,"salaryMax":580967,"salaryMean":332286},{"salaryTitle":"Automation Engineer","salaryTitleHi":null,"employeeDesignation":"Automation Engineer","employeeDesignationHi":null,"cmpRating":3.46,"noRatedBy":474,"salaryMin":275265,"salaryMax":856157,"salaryMean":497113},{"salaryTitle":"Other IT Software - Training & Development","salaryTitleHi":null,"employeeDesignation":"Other IT Software - Training & Development","employeeDesignationHi":null,"cmpRating":3.46,"noRatedBy":438,"salaryMin":261434,"salaryMax":880704,"salaryMean":471130},{"salaryTitle":"ERP, CRM Technical Consultant","salaryTitleHi":null,"employeeDesignation":"ERP, CRM Technical Consultant","employeeDesignationHi":null,"cmpRating":3.46,"noRatedBy":431,"salaryMin":304076,"salaryMax":1234965,"salaryMean":651223},{"salaryTitle":"Customer Care Executive/ Associate - Non Voice/ Web","salaryTitleHi":null,"employeeDesignation":"Customer Care Executive/ Associate - Non Voice/ Web","employeeDesignationHi":null,"cmpRating":3.46,"noRatedBy":415,"salaryMin":164868,"salaryMax":439339,"salaryMean":274217},{"salaryTitle":"Financial Analyst","salaryTitleHi":null,"employeeDesignation":"Financial Analyst","employeeDesignationHi":null,"cmpRating":3.46,"noRatedBy":393,"salaryMin":185194,"salaryMax":757494,"salaryMean":394956},{"salaryTitle":"ERP, CRM Developer","salaryTitleHi":null,"employeeDesignation":"ERP, CRM Developer","employeeDesignationHi":null,"cmpRating":3.46,"noRatedBy":377,"salaryMin":286429,"salaryMax":889672,"salaryMean":505999},{"salaryTitle":"Operations/ Process - Associate","salaryTitleHi":null,"employeeDesignation":"Operations/ Process - Associate","employeeDesignationHi":null,"cmpRating":3.46,"noRatedBy":377,"salaryMin":173302,"salaryMax":447543,"salaryMean":283160},{"salaryTitle":"ERP, CRM Functional Consultant","salaryTitleHi":null,"employeeDesignation":"ERP, CRM Functional Consultant","employeeDesignationHi":null,"cmpRating":3.46,"noRatedBy":368,"salaryMin":295550,"salaryMax":1418266,"salaryMean":688881},{"salaryTitle":"Investment Banking Analyst","salaryTitleHi":null,"employeeDesignation":"Investment Banking Analyst","employeeDesignationHi":null,"cmpRating":3.46,"noRatedBy":362,"salaryMin":206044,"salaryMax":815722,"salaryMean":438875},{"salaryTitle":"Operations Manager","salaryTitleHi":null,"employeeDesignation":"Operations Manager","employeeDesignationHi":null,"cmpRating":3.46,"noRatedBy":312,"salaryMin":293725,"salaryMax":1698383,"salaryMean":927969},{"salaryTitle":"Other Financial Services","salaryTitleHi":null,"employeeDesignation":"Other Financial Services","employeeDesignationHi":null,"cmpRating":3.46,"noRatedBy":304,"salaryMin":184566,"salaryMax":993700,"salaryMean":426772},{"salaryTitle":"Customer Care Executive/ Associate - Voice","salaryTitleHi":null,"employeeDesignation":"Customer Care Executive/ Associate - Voice","employeeDesignationHi":null,"cmpRating":3.46,"noRatedBy":302,"salaryMin":184533,"salaryMax":545733,"salaryMean":320991},{"salaryTitle":"Tech Architect","salaryTitleHi":null,"employeeDesignation":"Tech Architect","employeeDesignationHi":null,"cmpRating":3.46,"noRatedBy":300,"salaryMin":331266,"salaryMax":2338666,"salaryMean":1204412},{"salaryTitle":"Subject Matter Expert (SME)","salaryTitleHi":null,"employeeDesignation":"Subject Matter Expert (SME)","employeeDesignationHi":null,"cmpRating":3.46,"noRatedBy":295,"salaryMin":231234,"salaryMax":695313,"salaryMean":401560},{"salaryTitle":"Delivery Manager/ Head","salaryTitleHi":null,"employeeDesignation":"Delivery Manager/ Head","employeeDesignationHi":null,"cmpRating":3.46,"noRatedBy":288,"salaryMin":890192,"salaryMax":3010350,"salaryMean":1918210},{"salaryTitle":"Program Manager","salaryTitleHi":null,"employeeDesignation":"Program Manager","employeeDesignationHi":null,"cmpRating":3.46,"noRatedBy":287,"salaryMin":320835,"salaryMax":2677450,"salaryMean":1501038},{"salaryTitle":"Other IT Software - Business/ Systems Analysis","salaryTitleHi":null,"employeeDesignation":"Other IT Software - Business/ Systems Analysis","employeeDesignationHi":null,"cmpRating":3.46,"noRatedBy":276,"salaryMin":273018,"salaryMax":1298674,"salaryMean":579422},{"salaryTitle":"Performance Test Engineer","salaryTitleHi":null,"employeeDesignation":"Performance Test Engineer","employeeDesignationHi":null,"cmpRating":3.46,"noRatedBy":232,"salaryMin":276643,"salaryMax":850526,"salaryMean":490517},{"salaryTitle":"Software Testing Manager","salaryTitleHi":null,"employeeDesignation":"Software Testing Manager","employeeDesignationHi":null,"cmpRating":3.46,"noRatedBy":223,"salaryMin":400390,"salaryMax":1859490,"salaryMean":1134801},{"salaryTitle":"HR Executive/ Officer","salaryTitleHi":null,"employeeDesignation":"HR Executive/ Officer","employeeDesignationHi":null,"cmpRating":3.46,"noRatedBy":205,"salaryMin":185250,"salaryMax":647000,"salaryMean":386790},{"salaryTitle":"Database Architect/ Designer","salaryTitleHi":null,"employeeDesignation":"Database Architect/ Designer","employeeDesignationHi":null,"cmpRating":3.46,"noRatedBy":196,"salaryMin":281873,"salaryMax":1521300,"salaryMean":759089},{"salaryTitle":"Process Associate","salaryTitleHi":null,"employeeDesignation":"Process Associate","employeeDesignationHi":null,"cmpRating":3.46,"noRatedBy":193,"salaryMin":159468,"salaryMax":416900,"salaryMean":266784},{"salaryTitle":"Team Lead","salaryTitleHi":null,"employeeDesignation":"Team Lead","employeeDesignationHi":null,"cmpRating":3.46,"noRatedBy":193,"salaryMin":314226,"salaryMax":835015,"salaryMean":566132},{"salaryTitle":"Clinical Data Manager","salaryTitleHi":null,"employeeDesignation":"Clinical Data Manager","employeeDesignationHi":null,"cmpRating":3.46,"noRatedBy":186,"salaryMin":185877,"salaryMax":1030922,"salaryMean":492421},{"salaryTitle":"ERP, CRM Analyst","salaryTitleHi":null,"employeeDesignation":"ERP, CRM Analyst","employeeDesignationHi":null,"cmpRating":3.46,"noRatedBy":184,"salaryMin":290700,"salaryMax":859155,"salaryMean":465697},{"salaryTitle":"Financial Accountant","salaryTitleHi":null,"employeeDesignation":"Financial Accountant","employeeDesignationHi":null,"cmpRating":3.46,"noRatedBy":169,"salaryMin":193975,"salaryMax":688212,"salaryMean":396465},{"salaryTitle":"Other Investment Banking","salaryTitleHi":null,"employeeDesignation":"Other Investment Banking","employeeDesignationHi":null,"cmpRating":3.46,"noRatedBy":167,"salaryMin":199350,"salaryMax":1280100,"salaryMean":535414},{"salaryTitle":"System Engineer","salaryTitleHi":null,"employeeDesignation":"System Engineer","employeeDesignationHi":null,"cmpRating":3.46,"noRatedBy":160,"salaryMin":188637,"salaryMax":792912,"salaryMean":437845},{"salaryTitle":"Network Administrator","salaryTitleHi":null,"employeeDesignation":"Network Administrator","employeeDesignationHi":null,"cmpRating":3.46,"noRatedBy":153,"salaryMin":205766,"salaryMax":1115266,"salaryMean":602657},{"salaryTitle":"Other IT Software - ERP, CRM","salaryTitleHi":null,"employeeDesignation":"Other IT Software - ERP, CRM","employeeDesignationHi":null,"cmpRating":3.46,"noRatedBy":149,"salaryMin":242685,"salaryMax":1498342,"salaryMean":620286},{"salaryTitle":"Administrator","salaryTitleHi":null,"employeeDesignation":"Administrator","employeeDesignationHi":null,"cmpRating":3.46,"noRatedBy":141,"salaryMin":276514,"salaryMax":979385,"salaryMean":503580},{"salaryTitle":"Back Office Executive","salaryTitleHi":null,"employeeDesignation":"Back Office Executive","employeeDesignationHi":null,"cmpRating":3.46,"noRatedBy":141,"salaryMin":166614,"salaryMax":533714,"salaryMean":320020},{"salaryTitle":"System Security Engineer","salaryTitleHi":null,"employeeDesignation":"System Security Engineer","employeeDesignationHi":null,"cmpRating":3.46,"noRatedBy":141,"salaryMin":274157,"salaryMax":918514,"salaryMean":476055},{"salaryTitle":"Other IT Software - Maintenance/ Systems","salaryTitleHi":null,"employeeDesignation":"Other IT Software - Maintenance/ Systems","employeeDesignationHi":null,"cmpRating":3.46,"noRatedBy":139,"salaryMin":280215,"salaryMax":899323,"salaryMean":487932},{"salaryTitle":"Account Services Executive","salaryTitleHi":null,"employeeDesignation":"Account Services Executive","employeeDesignationHi":null,"cmpRating":3.46,"noRatedBy":136,"salaryMin":166961,"salaryMax":544392,"salaryMean":297468},{"salaryTitle":"Administration Assistant/ Executive","salaryTitleHi":null,"employeeDesignation":"Administration Assistant/ Executive","employeeDesignationHi":null,"cmpRating":3.46,"noRatedBy":136,"salaryMin":158646,"salaryMax":565992,"salaryMean":295826},{"salaryTitle":"Network Support Engineer","salaryTitleHi":null,"employeeDesignation":"Network Support Engineer","employeeDesignationHi":null,"cmpRating":3.46,"noRatedBy":134,"salaryMin":170169,"salaryMax":943523,"salaryMean":462758},{"salaryTitle":"Other IT Software - System Programming","salaryTitleHi":null,"employeeDesignation":"Other IT Software - System Programming","employeeDesignationHi":null,"cmpRating":3.46,"noRatedBy":131,"salaryMin":242976,"salaryMax":766938,"salaryMean":435649},{"salaryTitle":"Others","salaryTitleHi":null,"employeeDesignation":"Others","employeeDesignationHi":null,"cmpRating":3.46,"noRatedBy":128,"salaryMin":174050,"salaryMax":1034466,"salaryMean":450313},{"salaryTitle":"Intern","salaryTitleHi":null,"employeeDesignation":"Intern","employeeDesignationHi":null,"cmpRating":3.46,"noRatedBy":124,"salaryMin":188166,"salaryMax":729400,"salaryMean":385681},{"salaryTitle":"Operations/ Process - Team Lead","salaryTitleHi":null,"employeeDesignation":"Operations/ Process - Team Lead","employeeDesignationHi":null,"cmpRating":3.46,"noRatedBy":124,"salaryMin":298766,"salaryMax":810283,"salaryMean":547329},{"salaryTitle":"Operations Executive/ Officer","salaryTitleHi":null,"employeeDesignation":"Operations Executive/ Officer","employeeDesignationHi":null,"cmpRating":3.46,"noRatedBy":123,"salaryMin":181900,"salaryMax":697850,"salaryMean":355533},{"salaryTitle":"Other Finance","salaryTitleHi":null,"employeeDesignation":"Other Finance","employeeDesignationHi":null,"cmpRating":3.46,"noRatedBy":115,"salaryMin":179527,"salaryMax":699827,"salaryMean":359588},{"salaryTitle":"Other Doctor/ Nurse/ Healthcare Professional","salaryTitleHi":null,"employeeDesignation":"Other Doctor/ Nurse/ Healthcare Professional","employeeDesignationHi":null,"cmpRating":3.46,"noRatedBy":108,"salaryMin":192600,"salaryMax":799700,"salaryMean":409428},{"salaryTitle":"Web Designer","salaryTitleHi":null,"employeeDesignation":"Web Designer","employeeDesignationHi":null,"cmpRating":3.46,"noRatedBy":103,"salaryMin":250100,"salaryMax":844500,"salaryMean":466598},{"salaryTitle":"Operations/ Process - Manager","salaryTitleHi":null,"employeeDesignation":"Operations/ Process - Manager","employeeDesignationHi":null,"cmpRating":3.46,"noRatedBy":98,"salaryMin":570155,"salaryMax":1492700,"salaryMean":964220},{"salaryTitle":"Software Trainer","salaryTitleHi":null,"employeeDesignation":"Software Trainer","employeeDesignationHi":null,"cmpRating":3.46,"noRatedBy":98,"salaryMin":260355,"salaryMax":702455,"salaryMean":395302},{"salaryTitle":"Customer Service Executive/ Officer","salaryTitleHi":null,"employeeDesignation":"Customer Service Executive/ Officer","employeeDesignationHi":null,"cmpRating":3.46,"noRatedBy":93,"salaryMin":160577,"salaryMax":561733,"salaryMean":313886},{"salaryTitle":"Sales/ Business Development Manager","salaryTitleHi":null,"employeeDesignation":"Sales/ Business Development Manager","employeeDesignationHi":null,"cmpRating":3.46,"noRatedBy":93,"salaryMin":302744,"salaryMax":1733011,"salaryMean":1017307},{"salaryTitle":"Application Developer/ Programmer","salaryTitleHi":null,"employeeDesignation":"Application Developer/ Programmer","employeeDesignationHi":null,"cmpRating":3.46,"noRatedBy":90,"salaryMin":283844,"salaryMax":1094922,"salaryMean":547322},{"salaryTitle":"Other IT Software - Middleware","salaryTitleHi":null,"employeeDesignation":"Other IT Software - Middleware","employeeDesignationHi":null,"cmpRating":3.46,"noRatedBy":89,"salaryMin":291075,"salaryMax":1119525,"salaryMean":568177},{"salaryTitle":"Web Programmer","salaryTitleHi":null,"employeeDesignation":"Web Programmer","employeeDesignationHi":null,"cmpRating":3.46,"noRatedBy":88,"salaryMin":219300,"salaryMax":700850,"salaryMean":418934},{"salaryTitle":"HR Generalist","salaryTitleHi":null,"employeeDesignation":"HR Generalist","employeeDesignationHi":null,"cmpRating":3.46,"noRatedBy":87,"salaryMin":188775,"salaryMax":1205800,"salaryMean":536144},{"salaryTitle":"Data Management/ Statistics","salaryTitleHi":null,"employeeDesignation":"Data Management/ Statistics","employeeDesignationHi":null,"cmpRating":3.46,"noRatedBy":82,"salaryMin":188175,"salaryMax":1028050,"salaryMean":454415},{"salaryTitle":"Quality Assurance/ Control - Executive","salaryTitleHi":null,"employeeDesignation":"Quality Assurance/ Control - Executive","employeeDesignationHi":null,"cmpRating":3.46,"noRatedBy":81,"salaryMin":191950,"salaryMax":895025,"salaryMean":441680},{"salaryTitle":"Team Lead - Non Voice/ Web","salaryTitleHi":null,"employeeDesignation":"Team Lead - Non Voice/ Web","employeeDesignationHi":null,"cmpRating":3.46,"noRatedBy":81,"salaryMin":251025,"salaryMax":769150,"salaryMean":519261},{"salaryTitle":"Clinical Research/ Clinical Trials - Associate","salaryTitleHi":null,"employeeDesignation":"Clinical Research/ Clinical Trials - Associate","employeeDesignationHi":null,"cmpRating":3.46,"noRatedBy":80,"salaryMin":180400,"salaryMax":682700,"salaryMean":380388},{"salaryTitle":"Technical Support Associate (Non Voice)","salaryTitleHi":null,"employeeDesignation":"Technical Support Associate (Non Voice)","employeeDesignationHi":null,"cmpRating":3.46,"noRatedBy":80,"salaryMin":152625,"salaryMax":360125,"salaryMean":237576},{"salaryTitle":"Training & Development - Executive/ Officer","salaryTitleHi":null,"employeeDesignation":"Training & Development - Executive/ Officer","employeeDesignationHi":null,"cmpRating":3.46,"noRatedBy":75,"salaryMin":204342,"salaryMax":706828,"salaryMean":459011},{"salaryTitle":"Other IT Software - Security/ Operating Systems","salaryTitleHi":null,"employeeDesignation":"Other IT Software - Security/ Operating Systems","employeeDesignationHi":null,"cmpRating":3.46,"noRatedBy":74,"salaryMin":238185,"salaryMax":1079028,"salaryMean":566257},{"salaryTitle":"Research & Analytics - Associate","salaryTitleHi":null,"employeeDesignation":"Research & Analytics - Associate","employeeDesignationHi":null,"cmpRating":3.46,"noRatedBy":74,"salaryMin":193885,"salaryMax":540671,"salaryMean":322642},{"salaryTitle":"Quality - Coach/ Analyst","salaryTitleHi":null,"employeeDesignation":"Quality - Coach/ Analyst","employeeDesignationHi":null,"cmpRating":3.46,"noRatedBy":73,"salaryMin":203700,"salaryMax":529728,"salaryMean":371608},{"salaryTitle":"Software Testing Architect","salaryTitleHi":null,"employeeDesignation":"Software Testing Architect","employeeDesignationHi":null,"cmpRating":3.46,"noRatedBy":73,"salaryMin":222042,"salaryMax":1105914,"salaryMean":573412},{"salaryTitle":"Software Quality Assurance Manager","salaryTitleHi":null,"employeeDesignation":"Software Quality Assurance Manager","employeeDesignationHi":null,"cmpRating":3.46,"noRatedBy":72,"salaryMin":314528,"salaryMax":1947642,"salaryMean":1234260},{"salaryTitle":"User Interface Designer","salaryTitleHi":null,"employeeDesignation":"User Interface Designer","employeeDesignationHi":null,"cmpRating":3.46,"noRatedBy":72,"salaryMin":295942,"salaryMax":1133257,"salaryMean":639891},{"salaryTitle":"GUI/ Web Developer","salaryTitleHi":null,"employeeDesignation":"GUI/ Web Developer","employeeDesignationHi":null,"cmpRating":3.46,"noRatedBy":71,"salaryMin":282242,"salaryMax":919914,"salaryMean":500464},{"salaryTitle":"Product Manager","salaryTitleHi":null,"employeeDesignation":"Product Manager","employeeDesignationHi":null,"cmpRating":3.46,"noRatedBy":71,"salaryMin":327928,"salaryMax":2127642,"salaryMean":1154358},{"salaryTitle":"Other Accounting/ Audit","salaryTitleHi":null,"employeeDesignation":"Other Accounting/ Audit","employeeDesignationHi":null,"cmpRating":3.46,"noRatedBy":70,"salaryMin":188642,"salaryMax":589800,"salaryMean":355214},{"salaryTitle":"Technical Support Associate (Voice)","salaryTitleHi":null,"employeeDesignation":"Technical Support Associate (Voice)","employeeDesignationHi":null,"cmpRating":3.46,"noRatedBy":70,"salaryMin":191885,"salaryMax":534985,"salaryMean":322698},{"salaryTitle":"Other Call Centre/ Operations/ Customer Service","salaryTitleHi":null,"employeeDesignation":"Other Call Centre/ Operations/ Customer Service","employeeDesignationHi":null,"cmpRating":3.46,"noRatedBy":69,"salaryMin":163866,"salaryMax":751300,"salaryMean":319213},{"salaryTitle":"Technical Support Manager","salaryTitleHi":null,"employeeDesignation":"Technical Support Manager","employeeDesignationHi":null,"cmpRating":3.46,"noRatedBy":69,"salaryMin":309866,"salaryMax":1850700,"salaryMean":869502},{"salaryTitle":"Quality Auditor","salaryTitleHi":null,"employeeDesignation":"Quality Auditor","employeeDesignationHi":null,"cmpRating":3.46,"noRatedBy":68,"salaryMin":226700,"salaryMax":897566,"salaryMean":456024},{"salaryTitle":"System Integrator","salaryTitleHi":null,"employeeDesignation":"System Integrator","employeeDesignationHi":null,"cmpRating":3.46,"noRatedBy":67,"salaryMin":244966,"salaryMax":1013500,"salaryMean":539317},{"salaryTitle":"Management/ Business Consultant","salaryTitleHi":null,"employeeDesignation":"Management/ Business Consultant","employeeDesignationHi":null,"cmpRating":3.46,"noRatedBy":66,"salaryMin":672533,"salaryMax":1671133,"salaryMean":1177540},{"salaryTitle":"Equity Analyst","salaryTitleHi":null,"employeeDesignation":"Equity Analyst","employeeDesignationHi":null,"cmpRating":3.46,"noRatedBy":65,"salaryMin":202133,"salaryMax":1160066,"salaryMean":545630},{"salaryTitle":"Other Data Management/ Analysis","salaryTitleHi":null,"employeeDesignation":"Other Data Management/ Analysis","employeeDesignationHi":null,"cmpRating":3.46,"noRatedBy":65,"salaryMin":177300,"salaryMax":855233,"salaryMean":410694},{"salaryTitle":"Investment Analyst","salaryTitleHi":null,"employeeDesignation":"Investment Analyst","employeeDesignationHi":null,"cmpRating":3.46,"noRatedBy":62,"salaryMin":202033,"salaryMax":852900,"salaryMean":456058},{"salaryTitle":"Other IT Software - Animation/ Graphics/ Web Designing/ Usability","salaryTitleHi":null,"employeeDesignation":"Other IT Software - Animation/ Graphics/ Web Designing/ Usability","employeeDesignationHi":null,"cmpRating":3.46,"noRatedBy":62,"salaryMin":255066,"salaryMax":937566,"salaryMean":501989},{"salaryTitle":"Other Insurance","salaryTitleHi":null,"employeeDesignation":"Other Insurance","employeeDesignationHi":null,"cmpRating":3.46,"noRatedBy":60,"salaryMin":170866,"salaryMax":695066,"salaryMean":333028},{"salaryTitle":"ERP, CRM Support Engineer","salaryTitleHi":null,"employeeDesignation":"ERP, CRM Support Engineer","employeeDesignationHi":null,"cmpRating":3.46,"noRatedBy":57,"salaryMin":291666,"salaryMax":951733,"salaryMean":512648},{"salaryTitle":"Recruitment - Executive/ Officer","salaryTitleHi":null,"employeeDesignation":"Recruitment - Executive/ Officer","employeeDesignationHi":null,"cmpRating":3.46,"noRatedBy":57,"salaryMin":174033,"salaryMax":815866,"salaryMean":403838},{"salaryTitle":"Product Analyst/ Executive","salaryTitleHi":null,"employeeDesignation":"Product Analyst/ Executive","employeeDesignationHi":null,"cmpRating":3.46,"noRatedBy":55,"salaryMin":217300,"salaryMax":1191766,"salaryMean":500866},{"salaryTitle":"Operations/ Documentation - Executive/ Manager","salaryTitleHi":null,"employeeDesignation":"Operations/ Documentation - Executive/ Manager","employeeDesignationHi":null,"cmpRating":3.46,"noRatedBy":52,"salaryMin":191100,"salaryMax":833633,"salaryMean":431801},{"salaryTitle":"Other Back End/ Data/ Transaction Processing","salaryTitleHi":null,"employeeDesignation":"Other Back End/ Data/ Transaction Processing","employeeDesignationHi":null,"cmpRating":3.46,"noRatedBy":52,"salaryMin":197733,"salaryMax":432900,"salaryMean":294916},{"salaryTitle":"Other IT Software - Client Server","salaryTitleHi":null,"employeeDesignation":"Other IT Software - Client Server","employeeDesignationHi":null,"cmpRating":3.46,"noRatedBy":51,"salaryMin":240466,"salaryMax":823466,"salaryMean":456397},{"salaryTitle":"Documentation/ Medical Writer","salaryTitleHi":null,"employeeDesignation":"Documentation/ Medical Writer","employeeDesignationHi":null,"cmpRating":3.46,"noRatedBy":50,"salaryMin":240700,"salaryMax":981333,"salaryMean":498972},{"salaryTitle":"Other Top Management, IT Software - Others","salaryTitleHi":null,"employeeDesignation":"Other Top Management, IT Software - Others","employeeDesignationHi":null,"cmpRating":3.46,"noRatedBy":50,"salaryMin":270300,"salaryMax":948566,"salaryMean":461105},{"salaryTitle":"Other Administration","salaryTitleHi":null,"employeeDesignation":"Other Administration","employeeDesignationHi":null,"cmpRating":3.46,"noRatedBy":49,"salaryMin":156766,"salaryMax":749266,"salaryMean":339869},{"salaryTitle":"Pharmacist/ Chemist","salaryTitleHi":null,"employeeDesignation":"Pharmacist/ Chemist","employeeDesignationHi":null,"cmpRating":3.46,"noRatedBy":47,"salaryMin":197800,"salaryMax":534000,"salaryMean":331426},{"salaryTitle":"Transaction Processing Executive","salaryTitleHi":null,"employeeDesignation":"Transaction Processing Executive","employeeDesignationHi":null,"cmpRating":3.46,"noRatedBy":46,"salaryMin":185400,"salaryMax":450566,"salaryMean":320815},{"salaryTitle":"Other HCM/ HR/ T&D","salaryTitleHi":null,"employeeDesignation":"Other HCM/ HR/ T&D","employeeDesignationHi":null,"cmpRating":3.46,"noRatedBy":45,"salaryMin":178733,"salaryMax":584866,"salaryMean":361066},{"salaryTitle":"Director - Program Management","salaryTitleHi":null,"employeeDesignation":"Director - Program Management","employeeDesignationHi":null,"cmpRating":3.46,"noRatedBy":44,"salaryMin":1163333,"salaryMax":3901866,"salaryMean":2749044},{"salaryTitle":"Hardware Design Engineer","salaryTitleHi":null,"employeeDesignation":"Hardware Design Engineer","employeeDesignationHi":null,"cmpRating":3.46,"noRatedBy":44,"salaryMin":258433,"salaryMax":690700,"salaryMean":412279},{"salaryTitle":"Quality Assurance/ Control - Manager","salaryTitleHi":null,"employeeDesignation":"Quality Assurance/ Control - Manager","employeeDesignationHi":null,"cmpRating":3.46,"noRatedBy":44,"salaryMin":264800,"salaryMax":1944333,"salaryMean":1083238},{"salaryTitle":"Chartered Accountant","salaryTitleHi":null,"employeeDesignation":"Chartered Accountant","employeeDesignationHi":null,"cmpRating":3.46,"noRatedBy":42,"salaryMin":433233,"salaryMax":1539266,"salaryMean":787849},{"salaryTitle":"Credit Analyst/ Officer","salaryTitleHi":null,"employeeDesignation":"Credit Analyst/ Officer","employeeDesignationHi":null,"cmpRating":3.46,"noRatedBy":41,"salaryMin":213966,"salaryMax":796200,"salaryMean":409374},{"salaryTitle":"Process Flow/ Work Flow Analyst","salaryTitleHi":null,"employeeDesignation":"Process Flow/ Work Flow Analyst","employeeDesignationHi":null,"cmpRating":3.46,"noRatedBy":41,"salaryMin":198200,"salaryMax":661466,"salaryMean":411873},{"salaryTitle":"Team Lead - Voice","salaryTitleHi":null,"employeeDesignation":"Team Lead - Voice","employeeDesignationHi":null,"cmpRating":3.46,"noRatedBy":41,"salaryMin":388166,"salaryMax":767966,"salaryMean":571762},{"salaryTitle":"Other IT Software - E-Commerce/ Internet Technologies","salaryTitleHi":null,"employeeDesignation":"Other IT Software - E-Commerce/ Internet Technologies","employeeDesignationHi":null,"cmpRating":3.46,"noRatedBy":40,"salaryMin":240800,"salaryMax":958350,"salaryMean":484021},{"salaryTitle":"Visual Designer/ Animator","salaryTitleHi":null,"employeeDesignation":"Visual Designer/ Animator","employeeDesignationHi":null,"cmpRating":3.46,"noRatedBy":40,"salaryMin":224650,"salaryMax":924650,"salaryMean":530553},{"salaryTitle":"Derivatives Analyst","salaryTitleHi":null,"employeeDesignation":"Derivatives Analyst","employeeDesignationHi":null,"cmpRating":3.46,"noRatedBy":39,"salaryMin":201700,"salaryMax":863000,"salaryMean":403303},{"salaryTitle":"KPO, LPO Process/ Operations - Team Lead","salaryTitleHi":null,"employeeDesignation":"KPO, LPO Process/ Operations - Team Lead","employeeDesignationHi":null,"cmpRating":3.46,"noRatedBy":39,"salaryMin":279400,"salaryMax":896450,"salaryMean":560566},{"salaryTitle":"Other Top Management, IT Software - Operations/ Support Services","salaryTitleHi":null,"employeeDesignation":"Other Top Management, IT Software - Operations/ Support Services","employeeDesignationHi":null,"cmpRating":3.46,"noRatedBy":37,"salaryMin":241150,"salaryMax":1547100,"salaryMean":603310},{"salaryTitle":"Accounts Manager","salaryTitleHi":null,"employeeDesignation":"Accounts Manager","employeeDesignationHi":null,"cmpRating":3.46,"noRatedBy":36,"salaryMin":246300,"salaryMax":913300,"salaryMean":591033},{"salaryTitle":"Clinical Research/ Clinical Trials - Coordinator","salaryTitleHi":null,"employeeDesignation":"Clinical Research/ Clinical Trials - Coordinator","employeeDesignationHi":null,"cmpRating":3.46,"noRatedBy":36,"salaryMin":159100,"salaryMax":711950,"salaryMean":369422},{"salaryTitle":"Other Biotechnology/ Pharmaceutical/ R & D","salaryTitleHi":null,"employeeDesignation":"Other Biotechnology/ Pharmaceutical/ R & D","employeeDesignationHi":null,"cmpRating":3.46,"noRatedBy":35,"salaryMin":259150,"salaryMax":678000,"salaryMean":443144},{"salaryTitle":"Other Operations","salaryTitleHi":null,"employeeDesignation":"Other Operations","employeeDesignationHi":null,"cmpRating":3.46,"noRatedBy":35,"salaryMin":206950,"salaryMax":900800,"salaryMean":393574},{"salaryTitle":"Application Designer","salaryTitleHi":null,"employeeDesignation":"Application Designer","employeeDesignationHi":null,"cmpRating":3.46,"noRatedBy":34,"salaryMin":286300,"salaryMax":730400,"salaryMean":467635},{"salaryTitle":"Lecturer/ Professor/ Reader","salaryTitleHi":null,"employeeDesignation":"Lecturer/ Professor/ Reader","employeeDesignationHi":null,"cmpRating":3.46,"noRatedBy":34,"salaryMin":243000,"salaryMax":640100,"salaryMean":482866},{"salaryTitle":"Other IT Hardware - Networking","salaryTitleHi":null,"employeeDesignation":"Other IT Hardware - Networking","employeeDesignationHi":null,"cmpRating":3.46,"noRatedBy":34,"salaryMin":180250,"salaryMax":1064550,"salaryMean":527849},{"salaryTitle":"Maintenance Engineer","salaryTitleHi":null,"employeeDesignation":"Maintenance Engineer","employeeDesignationHi":null,"cmpRating":3.46,"noRatedBy":33,"salaryMin":303450,"salaryMax":706750,"salaryMean":442279},{"salaryTitle":"Facility Management - Executive","salaryTitleHi":null,"employeeDesignation":"Facility Management - Executive","employeeDesignationHi":null,"cmpRating":3.46,"noRatedBy":32,"salaryMin":184650,"salaryMax":715900,"salaryMean":314072},{"salaryTitle":"Other Banking","salaryTitleHi":null,"employeeDesignation":"Other Banking","employeeDesignationHi":null,"cmpRating":3.46,"noRatedBy":32,"salaryMin":184450,"salaryMax":1068850,"salaryMean":479793},{"salaryTitle":"Insurance Analyst - General Insurance","salaryTitleHi":null,"employeeDesignation":"Insurance Analyst - General Insurance","employeeDesignationHi":null,"cmpRating":3.46,"noRatedBy":31,"salaryMin":179800,"salaryMax":1181850,"salaryMean":440115},{"salaryTitle":"Data Entry/ DTP/ Data Conversion - Operator","salaryTitleHi":null,"employeeDesignation":"Data Entry/ DTP/ Data Conversion - Operator","employeeDesignationHi":null,"cmpRating":3.46,"noRatedBy":30,"salaryMin":164250,"salaryMax":360200,"salaryMean":237475},{"salaryTitle":"Operations Executive/ Officer - Insurance","salaryTitleHi":null,"employeeDesignation":"Operations Executive/ Officer - Insurance","employeeDesignationHi":null,"cmpRating":3.46,"noRatedBy":30,"salaryMin":191250,"salaryMax":511500,"salaryMean":315054},{"salaryTitle":"Other Logistics/ Supply Chain Management/ Procurement","salaryTitleHi":null,"employeeDesignation":"Other Logistics/ Supply Chain Management/ Procurement","employeeDesignationHi":null,"cmpRating":3.46,"noRatedBy":30,"salaryMin":189050,"salaryMax":1374450,"salaryMean":545961},{"salaryTitle":"Other Personal/ Retail Banking","salaryTitleHi":null,"employeeDesignation":"Other Personal/ Retail Banking","employeeDesignationHi":null,"cmpRating":3.46,"noRatedBy":30,"salaryMin":213400,"salaryMax":877600,"salaryMean":438263},{"salaryTitle":"Other Quality/ Process Control","salaryTitleHi":null,"employeeDesignation":"Other Quality/ Process Control","employeeDesignationHi":null,"cmpRating":3.46,"noRatedBy":29,"salaryMin":196150,"salaryMax":1564150,"salaryMean":594745},{"salaryTitle":"Finance Manager","salaryTitleHi":null,"employeeDesignation":"Finance Manager","employeeDesignationHi":null,"cmpRating":3.46,"noRatedBy":28,"salaryMin":284400,"salaryMax":1788400,"salaryMean":941473},{"salaryTitle":"Other Customer Service","salaryTitleHi":null,"employeeDesignation":"Other Customer Service","employeeDesignationHi":null,"cmpRating":3.46,"noRatedBy":28,"salaryMin":217550,"salaryMax":606050,"salaryMean":393081},{"salaryTitle":"Release Manager","salaryTitleHi":null,"employeeDesignation":"Release Manager","employeeDesignationHi":null,"cmpRating":3.46,"noRatedBy":28,"salaryMin":286850,"salaryMax":1111050,"salaryMean":553630},{"salaryTitle":"HR Consultant","salaryTitleHi":null,"employeeDesignation":"HR Consultant","employeeDesignationHi":null,"cmpRating":3.46,"noRatedBy":27,"salaryMin":175950,"salaryMax":704500,"salaryMean":386534},{"salaryTitle":"Other Top Management, IT Software - Application Programming","salaryTitleHi":null,"employeeDesignation":"Other Top Management, IT Software - Application Programming","employeeDesignationHi":null,"cmpRating":3.46,"noRatedBy":27,"salaryMin":278350,"salaryMax":806100,"salaryMean":456159},{"salaryTitle":"Pharmaceuticals - Research Analyst","salaryTitleHi":null,"employeeDesignation":"Pharmaceuticals - Research Analyst","employeeDesignationHi":null,"cmpRating":3.46,"noRatedBy":27,"salaryMin":184150,"salaryMax":526850,"salaryMean":349824},{"salaryTitle":"Business/ EDP Analyst","salaryTitleHi":null,"employeeDesignation":"Business/ EDP Analyst","employeeDesignationHi":null,"cmpRating":3.46,"noRatedBy":26,"salaryMin":309700,"salaryMax":685550,"salaryMean":470569},{"salaryTitle":"Other Sales/ Business Development","salaryTitleHi":null,"employeeDesignation":"Other Sales/ Business Development","employeeDesignationHi":null,"cmpRating":3.46,"noRatedBy":26,"salaryMin":306150,"salaryMax":1323100,"salaryMean":748712},{"salaryTitle":"Administration Manager","salaryTitleHi":null,"employeeDesignation":"Administration Manager","employeeDesignationHi":null,"cmpRating":3.46,"noRatedBy":25,"salaryMin":219850,"salaryMax":1094100,"salaryMean":569665},{"salaryTitle":"Clinical Research/ Clinical Trials - Research Manager","salaryTitleHi":null,"employeeDesignation":"Clinical Research/ Clinical Trials - Research Manager","employeeDesignationHi":null,"cmpRating":3.46,"noRatedBy":25,"salaryMin":266400,"salaryMax":1076950,"salaryMean":655134},{"salaryTitle":"Internal Auditor","salaryTitleHi":null,"employeeDesignation":"Internal Auditor","employeeDesignationHi":null,"cmpRating":3.46,"noRatedBy":25,"salaryMin":237200,"salaryMax":1090900,"salaryMean":508850},{"salaryTitle":"Other IT Software - MIS/ EDP","salaryTitleHi":null,"employeeDesignation":"Other IT Software - MIS/ EDP","employeeDesignationHi":null,"cmpRating":3.46,"noRatedBy":25,"salaryMin":231100,"salaryMax":1020600,"salaryMean":552236},{"salaryTitle":"Other IT Software - Networking","salaryTitleHi":null,"employeeDesignation":"Other IT Software - Networking","employeeDesignationHi":null,"cmpRating":3.46,"noRatedBy":25,"salaryMin":229850,"salaryMax":889150,"salaryMean":481834},{"salaryTitle":"Risk Management Analyst/ Manager","salaryTitleHi":null,"employeeDesignation":"Risk Management Analyst/ Manager","employeeDesignationHi":null,"cmpRating":3.46,"noRatedBy":25,"salaryMin":237800,"salaryMax":1735200,"salaryMean":748282},{"salaryTitle":"Training & Development - Manager","salaryTitleHi":null,"employeeDesignation":"Training & Development - Manager","employeeDesignationHi":null,"cmpRating":3.46,"noRatedBy":25,"salaryMin":471900,"salaryMax":1609450,"salaryMean":1069531},{"salaryTitle":"Content Developer/ Content Writer","salaryTitleHi":null,"employeeDesignation":"Content Developer/ Content Writer","employeeDesignationHi":null,"cmpRating":3.46,"noRatedBy":24,"salaryMin":206300,"salaryMax":676050,"salaryMean":391522},{"salaryTitle":"Finance Controller","salaryTitleHi":null,"employeeDesignation":"Finance Controller","employeeDesignationHi":null,"cmpRating":3.46,"noRatedBy":24,"salaryMin":228550,"salaryMax":1189650,"salaryMean":562449},{"salaryTitle":"Market Research - Analyst","salaryTitleHi":null,"employeeDesignation":"Market Research - Analyst","employeeDesignationHi":null,"cmpRating":3.46,"noRatedBy":24,"salaryMin":227200,"salaryMax":789550,"salaryMean":428402},{"salaryTitle":"Other Top Management, IT Software - Business/ Systems Analysis","salaryTitleHi":null,"employeeDesignation":"Other Top Management, IT Software - Business/ Systems Analysis","employeeDesignationHi":null,"cmpRating":3.46,"noRatedBy":24,"salaryMin":313650,"salaryMax":2455100,"salaryMean":1050403},{"salaryTitle":"Software Consultant","salaryTitleHi":null,"employeeDesignation":"Software Consultant","employeeDesignationHi":null,"cmpRating":3.46,"noRatedBy":24,"salaryMin":364050,"salaryMax":1330850,"salaryMean":870015},{"salaryTitle":"Trainer - Technical/ Process","salaryTitleHi":null,"employeeDesignation":"Trainer - Technical/ Process","employeeDesignationHi":null,"cmpRating":3.46,"noRatedBy":24,"salaryMin":246800,"salaryMax":595150,"salaryMean":404045},{"salaryTitle":"Switching/ Router Engineer","salaryTitleHi":null,"employeeDesignation":"Switching/ Router Engineer","employeeDesignationHi":null,"cmpRating":3.46,"noRatedBy":23,"salaryMin":332850,"salaryMax":829300,"salaryMean":532687},{"salaryTitle":"Team Manager - Non Voice/ Web","salaryTitleHi":null,"employeeDesignation":"Team Manager - Non Voice/ Web","employeeDesignationHi":null,"cmpRating":3.46,"noRatedBy":23,"salaryMin":599200,"salaryMax":1046550,"salaryMean":784140},{"salaryTitle":"Compliance & Control","salaryTitleHi":null,"employeeDesignation":"Compliance & Control","employeeDesignationHi":null,"cmpRating":3.46,"noRatedBy":22,"salaryMin":232650,"salaryMax":623150,"salaryMean":393022},{"salaryTitle":"Executive Assistant/ Executive Secretary","salaryTitleHi":null,"employeeDesignation":"Executive Assistant/ Executive Secretary","employeeDesignationHi":null,"cmpRating":3.46,"noRatedBy":22,"salaryMin":157800,"salaryMax":500400,"salaryMean":312782},{"salaryTitle":"HR Manager","salaryTitleHi":null,"employeeDesignation":"HR Manager","employeeDesignationHi":null,"cmpRating":3.46,"noRatedBy":22,"salaryMin":263700,"salaryMax":1533000,"salaryMean":825458},{"salaryTitle":"Information Systems (MIS) - Manager","salaryTitleHi":null,"employeeDesignation":"Information Systems (MIS) - Manager","employeeDesignationHi":null,"cmpRating":3.46,"noRatedBy":22,"salaryMin":301400,"salaryMax":937600,"salaryMean":459957},{"salaryTitle":"MIS Executive","salaryTitleHi":null,"employeeDesignation":"MIS Executive","employeeDesignationHi":null,"cmpRating":3.46,"noRatedBy":22,"salaryMin":249950,"salaryMax":573950,"salaryMean":399723},{"salaryTitle":"Technical/ IT Content Developer","salaryTitleHi":null,"employeeDesignation":"Technical/ IT Content Developer","employeeDesignationHi":null,"cmpRating":3.46,"noRatedBy":22,"salaryMin":253250,"salaryMax":829950,"salaryMean":560900},{"salaryTitle":"Finance/ Budgeting Manager","salaryTitleHi":null,"employeeDesignation":"Finance/ Budgeting Manager","employeeDesignationHi":null,"cmpRating":3.46,"noRatedBy":21,"salaryMin":203700,"salaryMax":733000,"salaryMean":425382},{"salaryTitle":"Hedge Fund Analyst/ Trader","salaryTitleHi":null,"employeeDesignation":"Hedge Fund Analyst/ Trader","employeeDesignationHi":null,"cmpRating":3.46,"noRatedBy":21,"salaryMin":209550,"salaryMax":1048200,"salaryMean":504731},{"salaryTitle":"Purchase/ Vendor Development - Executive","salaryTitleHi":null,"employeeDesignation":"Purchase/ Vendor Development - Executive","employeeDesignationHi":null,"cmpRating":3.46,"noRatedBy":21,"salaryMin":216650,"salaryMax":712900,"salaryMean":430332},{"salaryTitle":"Service/ Maintenance Engineer/ Manager","salaryTitleHi":null,"employeeDesignation":"Service/ Maintenance Engineer/ Manager","employeeDesignationHi":null,"cmpRating":3.46,"noRatedBy":21,"salaryMin":182200,"salaryMax":773200,"salaryMean":397716},{"salaryTitle":"Technical Support - Asst. Team Lead/ Mentor (Voice)","salaryTitleHi":null,"employeeDesignation":"Technical Support - Asst. Team Lead/ Mentor (Voice)","employeeDesignationHi":null,"cmpRating":3.46,"noRatedBy":21,"salaryMin":284500,"salaryMax":649250,"salaryMean":444100},{"salaryTitle":"Accounts Assistant/ Book Keeper","salaryTitleHi":null,"employeeDesignation":"Accounts Assistant/ Book Keeper","employeeDesignationHi":null,"cmpRating":3.46,"noRatedBy":20,"salaryMin":195400,"salaryMax":491450,"salaryMean":310691},{"salaryTitle":"Insurance Analyst - Life Insurance","salaryTitleHi":null,"employeeDesignation":"Insurance Analyst - Life Insurance","employeeDesignationHi":null,"cmpRating":3.46,"noRatedBy":20,"salaryMin":289000,"salaryMax":597700,"salaryMean":427975},{"salaryTitle":"KPO, LPO Process/ Operations - Manager","salaryTitleHi":null,"employeeDesignation":"KPO, LPO Process/ Operations - Manager","employeeDesignationHi":null,"cmpRating":3.46,"noRatedBy":20,"salaryMin":497150,"salaryMax":1700300,"salaryMean":1007116},{"salaryTitle":"Other IT Software - Mobile Technology","salaryTitleHi":null,"employeeDesignation":"Other IT Software - Mobile Technology","employeeDesignationHi":null,"cmpRating":3.46,"noRatedBy":20,"salaryMin":293050,"salaryMax":745850,"salaryMean":484345},{"salaryTitle":"Transitions/ Migrations Manager","salaryTitleHi":null,"employeeDesignation":"Transitions/ Migrations Manager","employeeDesignationHi":null,"cmpRating":3.46,"noRatedBy":20,"salaryMin":522650,"salaryMax":1712600,"salaryMean":986326},{"salaryTitle":"Accounting/ Auditing Clerk","salaryTitleHi":null,"employeeDesignation":"Accounting/ Auditing Clerk","employeeDesignationHi":null,"cmpRating":3.46,"noRatedBy":19,"salaryMin":178000,"salaryMax":514050,"salaryMean":317555},{"salaryTitle":"Bio/ Pharma Informatics - Research Associate","salaryTitleHi":null,"employeeDesignation":"Bio/ Pharma Informatics - Research Associate","employeeDesignationHi":null,"cmpRating":3.46,"noRatedBy":19,"salaryMin":299800,"salaryMax":532150,"salaryMean":393677},{"salaryTitle":"ERP, CRM Manager","salaryTitleHi":null,"employeeDesignation":"ERP, CRM Manager","employeeDesignationHi":null,"cmpRating":3.46,"noRatedBy":19,"salaryMin":931350,"salaryMax":2135200,"salaryMean":1531067},{"salaryTitle":"Insurance - Claims Manager","salaryTitleHi":null,"employeeDesignation":"Insurance - Claims Manager","employeeDesignationHi":null,"cmpRating":3.46,"noRatedBy":19,"salaryMin":203200,"salaryMax":566550,"salaryMean":343752},{"salaryTitle":"Other Knowledge Based Services","salaryTitleHi":null,"employeeDesignation":"Other Knowledge Based Services","employeeDesignationHi":null,"cmpRating":3.46,"noRatedBy":19,"salaryMin":200550,"salaryMax":443600,"salaryMean":309181},{"salaryTitle":"Other Production/ Maintenance","salaryTitleHi":null,"employeeDesignation":"Other Production/ Maintenance","employeeDesignationHi":null,"cmpRating":3.46,"noRatedBy":19,"salaryMin":181150,"salaryMax":852700,"salaryMean":385972},{"salaryTitle":"Other Top Management, IT Software - DataBase, Datawarehousing","salaryTitleHi":null,"employeeDesignation":"Other Top Management, IT Software - DataBase, Datawarehousing","employeeDesignationHi":null,"cmpRating":3.46,"noRatedBy":19,"salaryMin":304900,"salaryMax":1447900,"salaryMean":685934},{"salaryTitle":"Relationship Executive/ Manager","salaryTitleHi":null,"employeeDesignation":"Relationship Executive/ Manager","employeeDesignationHi":null,"cmpRating":3.46,"noRatedBy":19,"salaryMin":204300,"salaryMax":550500,"salaryMean":358978},{"salaryTitle":"Asset Operations Executive/ Manager","salaryTitleHi":null,"employeeDesignation":"Asset Operations Executive/ Manager","employeeDesignationHi":null,"cmpRating":3.46,"noRatedBy":18,"salaryMin":204100,"salaryMax":826700,"salaryMean":459151},{"salaryTitle":"Other Telecom - Operations/ Support","salaryTitleHi":null,"employeeDesignation":"Other Telecom - Operations/ Support","employeeDesignationHi":null,"cmpRating":3.46,"noRatedBy":18,"salaryMin":241600,"salaryMax":1147150,"salaryMean":610039},{"salaryTitle":"Other Top Management","salaryTitleHi":null,"employeeDesignation":"Other Top Management","employeeDesignationHi":null,"cmpRating":3.46,"noRatedBy":18,"salaryMin":702900,"salaryMax":3190850,"salaryMean":1801842},{"salaryTitle":"Compensation & Benefits/ Rewards - Executive/ Officer","salaryTitleHi":null,"employeeDesignation":"Compensation & Benefits/ Rewards - Executive/ Officer","employeeDesignationHi":null,"cmpRating":3.46,"noRatedBy":17,"salaryMin":178150,"salaryMax":569700,"salaryMean":349269},{"salaryTitle":"Customer Service Manager/ Head","salaryTitleHi":null,"employeeDesignation":"Customer Service Manager/ Head","employeeDesignationHi":null,"cmpRating":3.46,"noRatedBy":17,"salaryMin":332950,"salaryMax":2745600,"salaryMean":1358966},{"salaryTitle":"Other Corporate Planning/ Strategic Management","salaryTitleHi":null,"employeeDesignation":"Other Corporate Planning/ Strategic Management","employeeDesignationHi":null,"cmpRating":3.46,"noRatedBy":17,"salaryMin":193650,"salaryMax":1529600,"salaryMean":777266},{"salaryTitle":"Cost Accountant/ ICWA","salaryTitleHi":null,"employeeDesignation":"Cost Accountant/ ICWA","employeeDesignationHi":null,"cmpRating":3.46,"noRatedBy":16,"salaryMin":271350,"salaryMax":1079100,"salaryMean":555758},{"salaryTitle":"IT Sales/ Technical Sales - Executive","salaryTitleHi":null,"employeeDesignation":"IT Sales/ Technical Sales - Executive","employeeDesignationHi":null,"cmpRating":3.46,"noRatedBy":16,"salaryMin":354300,"salaryMax":1065100,"salaryMean":687207},{"salaryTitle":"Mutual Fund Analyst","salaryTitleHi":null,"employeeDesignation":"Mutual Fund Analyst","employeeDesignationHi":null,"cmpRating":3.46,"noRatedBy":16,"salaryMin":205850,"salaryMax":786750,"salaryMean":426973},{"salaryTitle":"Recruitment Consultant","salaryTitleHi":null,"employeeDesignation":"Recruitment Consultant","employeeDesignationHi":null,"cmpRating":3.46,"noRatedBy":16,"salaryMin":291200,"salaryMax":539400,"salaryMean":421274},{"salaryTitle":"Content Services - Associate","salaryTitleHi":null,"employeeDesignation":"Content Services - Associate","employeeDesignationHi":null,"cmpRating":3.46,"noRatedBy":15,"salaryMin":194833,"salaryMax":505300,"salaryMean":342112},{"salaryTitle":"Security/ Equity Researcher","salaryTitleHi":null,"employeeDesignation":"Security/ Equity Researcher","employeeDesignationHi":null,"cmpRating":3.46,"noRatedBy":15,"salaryMin":342433,"salaryMax":1151533,"salaryMean":688307},{"salaryTitle":"Bio-Statistician","salaryTitleHi":null,"employeeDesignation":"Bio-Statistician","employeeDesignationHi":null,"cmpRating":3.46,"noRatedBy":14,"salaryMin":249566,"salaryMax":1243266,"salaryMean":631822}]},"getCompanyProsCons":{"reviewCount":2886,"pros":[{"count":507,"name":"Work-Life Balance","nameHi":null},{"count":494,"name":"Work Environment","nameHi":null},{"count":474,"name":"People/Colleagues","nameHi":null},{"count":421,"name":"Brand Name","nameHi":null},{"count":346,"name":"Quality of Work","nameHi":null}],"cons":[{"count":581,"name":"Salary","nameHi":null},{"count":445,"name":"No Work from Home","nameHi":null},{"count":382,"name":"Average Yearly Appraisal","nameHi":null},{"count":284,"name":"Limited Onsite Opportunities","nameHi":null},{"count":262,"name":"Limited Career Growth Opportunities","nameHi":null}]},"companyInfo":{"Founded":"1994","Founder":null,"FounderHi":null,"Employees":"10001+","Turnover":"10000+","Headquarters":"Teaneck, New Jersey, United States","HeadquartersHi":null,"Industry":[{"slug":"technology-it","name":null,"nameHi":null},{"slug":"telecom","name":null,"nameHi":null},{"slug":"dot-com-etc","name":null,"nameHi":null}],"Website":"http://www.cognizant.com/"},"googleCompanyResponse":{"itemListElement":[{"resultScore":13531.1103515625,"result":{"url":"http://www.cognizant.com/","detailedDescription":{"license":"https://en.wikipedia.org/wiki/Wikipedia:Text_of_Creative_Commons_Attribution-ShareAlike_3.0_Unported_License","url":"https://en.wikipedia.org/wiki/Cognizant","articleBody":"Cognizant is an American multinational product led digital corporation that provides digital products, digital IT services, including digital, technology, consulting, and operations services. ","articleBodyHi":"कॉग्निजेंट एक अमेरिकी बहुराष्ट्रीय उत्पाद है, जो डिजिटल कॉर्पोरेशन का नेतृत्व करता है, जो डिजिटल उत्पादों, डिजिटल आईटी सेवाओं को प्रदान करता है, जिसमें डिजिटल, प्रौद्योगिकी, परामर्श और संचालन सेवाएं शामिल हैं,"},"image":null,"description":"Corporation","descriptionHi":null,"name":"Cognizant","nameHi":null,"imageName":"cognizant.png"}}]},"dateCreated":"2021-01-03T18:52:44.066Z","dateModified":"2021-01-03T18:52:44.066Z","id":57,"slug":"cognizant-technology-solutions","recommendations":[{"companySeoName":"ksolves","companyName":"Ksolves","imageExist":"False","Industry":[{"name":"Technology (IT","slug":"technology-it"},{"name":" Telecom","slug":"telecom"},{"name":" Dot Com etc)","slug":"dot-com-etc"}],"imageUrl":"47639.png","total":0},{"companySeoName":"rudra-automation-pvt-ltd","companyName":"Rudra Automation Pvt Ltd","imageExist":"False","Industry":[{"name":"Technology (IT","slug":"technology-it"},{"name":" Telecom","slug":"telecom"},{"name":" Dot Com etc)","slug":"dot-com-etc"}],"imageUrl":"46784.png","total":0},{"companySeoName":"radical-logix","companyName":"Radical Logix","imageExist":"False","Industry":[{"name":"Technology (IT","slug":"technology-it"},{"name":" Telecom","slug":"telecom"},{"name":" Dot Com etc)","slug":"dot-com-etc"}],"imageUrl":"46213.png","total":0},{"companySeoName":"eigerlab-technologies","companyName":"Eigerlab Technologies","imageExist":"False","Industry":[{"name":"Technology - IT","slug":"technology-it"},{"name":" Telecom","slug":"telecom"},{"name":" Semiconductors","slug":"semiconductors"}],"imageUrl":"46210.png","total":0},{"companySeoName":"ginger-webs","companyName":"Ginger Webs","imageExist":"False","Industry":[{"name":"Technology (IT","slug":"technology-it"},{"name":" Telecom","slug":"telecom"},{"name":" Dot Com etc)","slug":"dot-com-etc"}],"imageUrl":"46195.png","total":0},{"companySeoName":"quillhash-technologies","companyName":"Quillhash Technologies","imageExist":"False","Industry":[{"name":"Technology - IT","slug":"technology-it"},{"name":" Telecom","slug":"telecom"},{"name":" Semiconductors","slug":"semiconductors"}],"imageUrl":"46174.png","total":0},{"companySeoName":"ans-it-services-pvt-ltd","companyName":"ANS IT Services Pvt. Ltd.","imageExist":"False","Industry":[{"name":"Technology - IT","slug":"technology-it"},{"name":" Telecom","slug":"telecom"},{"name":" Semiconductors","slug":"semiconductors"}],"imageUrl":"46161.png","total":0},{"companySeoName":"vedansh-technology-pvt-ltd","companyName":"Vedansh technology Pvt Ltd","imageExist":"False","Industry":[{"name":"Technology (IT","slug":"technology-it"},{"name":" Telecom","slug":"telecom"},{"name":" Dot Com etc)","slug":"dot-com-etc"}],"imageUrl":"46151.png","total":0},{"companySeoName":"unified-cloud-pvt-ltd","companyName":"Unified Cloud Pvt Ltd","imageExist":"False","Industry":[{"name":"Technology (IT","slug":"technology-it"},{"name":" Telecom","slug":"telecom"},{"name":" Dot Com etc)","slug":"dot-com-etc"}],"imageUrl":"46134.png","total":0},{"companySeoName":"avologi-infotech-private-limited","companyName":"AVOLOGI INFOTECH PRIVATE LIMITED","imageExist":"False","Industry":[{"name":"Technology (IT","slug":"technology-it"},{"name":" Telecom","slug":"telecom"},{"name":" Dot Com etc)","slug":"dot-com-etc"}],"imageUrl":"46089.png","total":0},{"companySeoName":"redblack-tree-technologies","companyName":"RedBlack Tree Technologies","imageExist":"False","Industry":[{"name":"Technology (IT","slug":"technology-it"},{"name":" Telecom","slug":"telecom"},{"name":" Dot Com etc)","slug":"dot-com-etc"}],"imageUrl":"46056.png","total":0},{"companySeoName":"souq","companyName":"Souq","imageExist":"False","Industry":[{"name":"Technology (IT","slug":"technology-it"},{"name":" Telecom","slug":"telecom"},{"name":" Dot Com etc)","slug":"dot-com-etc"}],"imageUrl":"46014.png","total":0}],"imageUrl":"57.png","updatedAt":"2026-03-24T17:06:12.713Z"}