{"page":126,"total":44860,"pageSize":24,"companies":[{"slug":"indusind-bank-ltd","name":"IndusInd Bank Ltd","name_hi":null,"location":null,"rating":null,"image_url":"644.png","image_exist":true,"industries":"banking,financial-services-insurance"},{"slug":"indusind-media-communications-ltd","name":"IndusInd Media & Communications Ltd ","name_hi":null,"location":null,"rating":null,"image_url":"3370.png","image_exist":true,"industries":"media,entertainment,advertising-related-services"},{"slug":"industrial-boilers-ltd","name":"Industrial Boilers Ltd ","name_hi":null,"location":null,"rating":null,"image_url":"7013.png","image_exist":true,"industries":"heavy-machinerycapital-goods-industrial-supplies"},{"slug":"industrial-solvent-chemicals-pvt-ltd","name":"Industrial Solvent & Chemicals Pvt Ltd ","name_hi":null,"location":null,"rating":null,"image_url":"4551.png","image_exist":true,"industries":"chemicals,paints-fertilizers"},{"slug":"industrias-metalurgicas-pescarmona-s-a","name":"Industrias Metalurgicas Pescarmona S.A ","name_hi":null,"location":null,"rating":null,"image_url":"3347.png","image_exist":true,"industries":"oil,gas-power-energy"},{"slug":"indwell-construction-pvt-ltd","name":"Indwell Construction Pvt Ltd ","name_hi":null,"location":null,"rating":null,"image_url":"2398.png","image_exist":true,"industries":"construction,interiors-real-estate-services"},{"slug":"infineon-technologies-pvt-ltd","name":"Infineon Technologies Pvt Ltd","name_hi":null,"location":null,"rating":null,"image_url":"645.png","image_exist":true,"industries":"technology-it,telecom,dot-com-etc"},{"slug":"infinite-computer-solutions-india-ltd","name":"Infinite Computer Solutions (India) Ltd","name_hi":null,"location":null,"rating":null,"image_url":"2414.png","image_exist":true,"industries":"technology-it,telecom,dot-com-etc"},{"slug":"infinite-computing-systems-pvt-ltd","name":"Infinite Computing Systems Pvt Ltd ","name_hi":null,"location":null,"rating":null,"image_url":"8490.png","image_exist":true,"industries":"technology-it,telecom,dot-com-etc"},{"slug":"infinite-journeys-pvt-ltd","name":"Infinite Journeys Pvt. Ltd.","name_hi":null,"location":null,"rating":null,"image_url":"45263.png","image_exist":true,"industries":"hospitality-tourism"},{"slug":"infiniti-retail-ltd","name":"Infiniti Retail Ltd","name_hi":null,"location":null,"rating":null,"image_url":"646.png","image_exist":true,"industries":"retail,shops,malls"},{"slug":"infinity-industries-pvt-ltd","name":"Infinity Industries Pvt Ltd","name_hi":null,"location":null,"rating":null,"image_url":"3159.png","image_exist":true,"industries":"agriculture,dairy,agro-based-industries,fishing,forestry"},{"slug":"infinium-india-ltd","name":"Infinium India Ltd ","name_hi":null,"location":null,"rating":null,"image_url":"5985.png","image_exist":true,"industries":"technology-it,telecom,dot-com-etc"},{"slug":"inflow-technologies-pvt-ltd","name":"Inflow Technologies Pvt Ltd ","name_hi":null,"location":null,"rating":null,"image_url":"3590.png","image_exist":true,"industries":"technology-it,telecom,dot-com-etc"},{"slug":"info-edge-india-ltd","name":"Info Edge (India) Ltd","name_hi":null,"location":null,"rating":null,"image_url":"647.png","image_exist":true,"industries":"technology-it,telecom,dot-com-etc"},{"slug":"info-electronics-systems-india-pvt-ltd","name":"Info Electronics Systems India Pvt Ltd ","name_hi":null,"location":null,"rating":null,"image_url":"4873.png","image_exist":true,"industries":"technology-it,telecom,dot-com-etc"},{"slug":"info-drive-software-ltd","name":"Info-Drive Software Ltd","name_hi":null,"location":null,"rating":null,"image_url":"2596.png","image_exist":true,"industries":"bpos,kpos,lpos,ites,transcription"},{"slug":"infopro-india-pvt-ltd","name":"InfoPro India Pvt Ltd ","name_hi":null,"location":null,"rating":null,"image_url":"2451.png","image_exist":true,"industries":"technology-it,telecom,dot-com-etc"},{"slug":"infostep-india-pvt-ltd","name":"InfoSTEP India Pvt Ltd ","name_hi":null,"location":null,"rating":null,"image_url":"3491.png","image_exist":true,"industries":"technology-it,telecom,dot-com-etc"},{"slug":"infosoft-global-pvt-ltd","name":"InfoSoft Global Pvt Ltd ","name_hi":null,"location":null,"rating":null,"image_url":"5983.png","image_exist":true,"industries":"technology-it,telecom,dot-com-etc"},{"slug":"infoapps-technologies-india-pvt-ltd","name":"Infoapps Technologies (India) Pvt Ltd","name_hi":null,"location":null,"rating":null,"image_url":"648.png","image_exist":true,"industries":"technology-it,telecom,dot-com-etc"},{"slug":"infocepts-technologies-pvt-ltd","name":"Infocepts Technologies Pvt Ltd","name_hi":null,"location":null,"rating":null,"image_url":"6795.png","image_exist":true,"industries":"technology-it,telecom,dot-com-etc"},{"slug":"infocom-network-ltd","name":"Infocom Network Ltd","name_hi":null,"location":null,"rating":null,"image_url":"3917.png","image_exist":true,"industries":"technology-it,telecom,dot-com-etc"},{"slug":"infoesearch-ites-pvt-ltd","name":"Infoesearch ITES Pvt Ltd","name_hi":null,"location":null,"rating":null,"image_url":"5523.png","image_exist":true,"industries":"media,entertainment,advertising-related-services"}],"updatedAt":"2026-03-24T17:02:50.329Z"}