{"page":1703,"total":44860,"pageSize":24,"companies":[{"slug":"thidiff-technologies","name":"ThiDiff Technologies","name_hi":null,"location":null,"rating":null,"image_url":"48979.png","image_exist":false,"industries":"other-technology-services"},{"slug":"think-learn-pvt-ltd","name":"Think & Learn Pvt Ltd.","name_hi":null,"location":null,"rating":null,"image_url":"45736.png","image_exist":false,"industries":"education,training-institutes-academic-research"},{"slug":"think-360-solutions-private-limited","name":"Think 360 Solutions Private Limited","name_hi":null,"location":null,"rating":null,"image_url":"46622.png","image_exist":false,"industries":null},{"slug":"think-future-technologies-pvt-ltd","name":"Think Future Technologies Pvt Ltd","name_hi":null,"location":null,"rating":null,"image_url":"46246.png","image_exist":false,"industries":null},{"slug":"think-infotech","name":"Think Infotech","name_hi":null,"location":null,"rating":null,"image_url":"44795.png","image_exist":false,"industries":"technology-it,telecom,dot-com-etc"},{"slug":"thinkbridge","name":"ThinkBridge","name_hi":null,"location":null,"rating":null,"image_url":"47407.png","image_exist":false,"industries":"other-technology-services"},{"slug":"thinknext-technologies-pvt-ltd","name":"ThinkNEXT Technologies Pvt. Ltd.","name_hi":null,"location":null,"rating":null,"image_url":"47380.png","image_exist":false,"industries":"other-technology-services"},{"slug":"thinkpalm","name":"ThinkPalm","name_hi":null,"location":null,"rating":null,"image_url":"46989.png","image_exist":false,"industries":null},{"slug":"thinkpalm-technologies-pvt-ltd","name":"ThinkPalm Technologies Pvt. Ltd.","name_hi":null,"location":null,"rating":null,"image_url":"48911.png","image_exist":false,"industries":"other-technology-services"},{"slug":"thinkquotient-software","name":"ThinkQuotient Software","name_hi":null,"location":null,"rating":null,"image_url":"47921.png","image_exist":false,"industries":"other-technology-services"},{"slug":"thinkbiz-solutions","name":"Thinkbiz Solutions","name_hi":null,"location":null,"rating":null,"image_url":"47731.png","image_exist":false,"industries":"other-technology-services"},{"slug":"thinking-hat-llp","name":"Thinking Hat Llp","name_hi":null,"location":null,"rating":null,"image_url":"46597.png","image_exist":false,"industries":null},{"slug":"thinkitive-technologies-private-limited","name":"Thinkitive Technologies Private Limited","name_hi":null,"location":null,"rating":null,"image_url":"47907.png","image_exist":false,"industries":"other-technology-services"},{"slug":"thinktank-infotech","name":"Thinktank Infotech","name_hi":null,"location":null,"rating":null,"image_url":"50926.png","image_exist":false,"industries":"other-technology-services"},{"slug":"thinkwik","name":"Thinkwik","name_hi":null,"location":null,"rating":null,"image_url":"47060.png","image_exist":false,"industries":null},{"slug":"third-rock-techkno","name":"Third Rock Techkno","name_hi":null,"location":null,"rating":null,"image_url":"47098.png","image_exist":false,"industries":null},{"slug":"thomasmount-consulting-pvt-ltd","name":"ThomasMount Consulting Pvt Ltd","name_hi":null,"location":null,"rating":null,"image_url":"50874.png","image_exist":false,"industries":"other-consultancy-services"},{"slug":"thoughtfocus-technologies","name":"ThoughtFocus Technologies","name_hi":null,"location":null,"rating":null,"image_url":"8980.png","image_exist":false,"industries":"technology-it,telecom,dot-com-etc"},{"slug":"thoughtspot","name":"ThoughtSpot","name_hi":null,"location":null,"rating":null,"image_url":"50564.png","image_exist":false,"industries":"other-technology-services"},{"slug":"thoughtful-minds","name":"Thoughtful Minds","name_hi":null,"location":null,"rating":null,"image_url":"49959.png","image_exist":false,"industries":"other-technology-services"},{"slug":"threadsol","name":"ThreadSol","name_hi":null,"location":null,"rating":null,"image_url":"47808.png","image_exist":false,"industries":"other-textiles,fashion,accessories-manufacturing"},{"slug":"threedots-consultancy-pvt-ltd","name":"Threedots Consultancy Pvt. Ltd.","name_hi":null,"location":null,"rating":null,"image_url":"49157.png","image_exist":false,"industries":"other-consultancy-services"},{"slug":"thriarr-polymers-pvt-ltd","name":"Thriarr Polymers Pvt Ltd","name_hi":null,"location":null,"rating":null,"image_url":"9423.png","image_exist":false,"industries":"chemicals,paints-fertilizers"},{"slug":"thrikasa-technologies","name":"Thrikasa Technologies","name_hi":null,"location":null,"rating":null,"image_url":"51607.png","image_exist":false,"industries":"other-technology-services"}],"updatedAt":"2026-03-24T17:03:44.619Z"}