{"page":1799,"total":44860,"pageSize":24,"companies":[{"slug":"winzest-pvt-ltd","name":"WINZEST PVT. LTD","name_hi":null,"location":null,"rating":null,"image_url":"43391.png","image_exist":false,"industries":"other-industry"},{"slug":"wipl","name":"WIPL","name_hi":null,"location":null,"rating":null,"image_url":"49926.png","image_exist":false,"industries":"other-technology-services"},{"slug":"wipro-infotech-partner-payroll","name":"WIPRO INFOTECH (PARTNER PAYROLL)","name_hi":null,"location":null,"rating":null,"image_url":"43349.png","image_exist":false,"industries":"other-industry"},{"slug":"wipro-infotech-renovision","name":"WIPRO INFOTECH(RENOVISION)","name_hi":null,"location":null,"rating":null,"image_url":"43318.png","image_exist":false,"industries":"other-industry"},{"slug":"wipro-water","name":"WIPRO WATER","name_hi":null,"location":null,"rating":null,"image_url":"43376.png","image_exist":false,"industries":"other-industry"},{"slug":"wiprowipro-technologies-hyderabad","name":"WIPROWIPRO TECHNOLOGIES HYDERABAD","name_hi":null,"location":null,"rating":null,"image_url":"43387.png","image_exist":false,"industries":"other-industry"},{"slug":"wiraswasta","name":"WIRASWASTA","name_hi":null,"location":null,"rating":null,"image_url":"43367.png","image_exist":false,"industries":"other-industry"},{"slug":"wire-and-wireless-india-ltd","name":"WIRE AND WIRELESS INDIA LTD","name_hi":null,"location":null,"rating":null,"image_url":"43194.png","image_exist":false,"industries":"media,entertainment,advertising-related-services"},{"slug":"wireless-communication","name":"WIRELESS COMMUNICATION","name_hi":null,"location":null,"rating":null,"image_url":"43393.png","image_exist":false,"industries":"banking,financial-services-insurance"},{"slug":"wireless-tt-info-services-ltd","name":"WIRELESS TT INFO SERVICES LTD","name_hi":null,"location":null,"rating":null,"image_url":"43237.png","image_exist":false,"industries":"technology-it,telecom,dot-com-etc"},{"slug":"wirkle-technologies","name":"WIRKLE TECHNOLOGIES","name_hi":null,"location":null,"rating":null,"image_url":"43380.png","image_exist":false,"industries":"technology-it,telecom,dot-com-etc"},{"slug":"wisdom-info-tech","name":"WISDOM INFO TECH","name_hi":null,"location":null,"rating":null,"image_url":"43229.png","image_exist":false,"industries":"other-industry"},{"slug":"wisdom-mart","name":"WISDOM MART","name_hi":null,"location":null,"rating":null,"image_url":"43344.png","image_exist":false,"industries":"other-industry"},{"slug":"wisdom-soft-solutions","name":"WISDOM SOFT SOLUTIONS","name_hi":null,"location":null,"rating":null,"image_url":"43204.png","image_exist":false,"industries":"other-industry"},{"slug":"wisdom-technologies","name":"WISDOM TECHNOLOGIES","name_hi":null,"location":null,"rating":null,"image_url":"43261.png","image_exist":false,"industries":"technology-it,telecom,dot-com-etc"},{"slug":"wisenic-data-services","name":"WISENIC DATA SERVICES","name_hi":null,"location":null,"rating":null,"image_url":"43389.png","image_exist":false,"industries":"technology-it,telecom,dot-com-etc"},{"slug":"wish-net-private-limited","name":"WISH NET PRIVATE LIMITED","name_hi":null,"location":null,"rating":null,"image_url":"43372.png","image_exist":false,"industries":"infrastructure-development-airports,ports,sezs,roads,rail-etc"},{"slug":"wish-net-private-limited-broad-band-company","name":"WISH NET PRIVATE LIMITED BROAD BAND COMPANY","name_hi":null,"location":null,"rating":null,"image_url":"43306.png","image_exist":false,"industries":"other-industry"},{"slug":"wishnet-pvt-ltd","name":"WISHNET PVT. LTD.","name_hi":null,"location":null,"rating":null,"image_url":"43220.png","image_exist":false,"industries":"other-industry"},{"slug":"wisitech-infosolutions-pvt-ltd","name":"WISITECH INFOSOLUTIONS PVT. LTD.","name_hi":null,"location":null,"rating":null,"image_url":"43270.png","image_exist":false,"industries":"technology-it,telecom,dot-com-etc"},{"slug":"wisor-telecom","name":"WISOR TELECOM","name_hi":null,"location":null,"rating":null,"image_url":"43255.png","image_exist":false,"industries":"bpos,kpos,lpos,ites,transcription"},{"slug":"wissen-systems","name":"WISSEN SYSTEMS","name_hi":null,"location":null,"rating":null,"image_url":"43330.png","image_exist":false,"industries":"technology-it,telecom,dot-com-etc"},{"slug":"witco-india-pvt-ltd","name":"WITCO INDIA PVT LTD","name_hi":null,"location":null,"rating":null,"image_url":"43202.png","image_exist":false,"industries":"retail,shops,malls"},{"slug":"withheld","name":"WITHHELD","name_hi":null,"location":null,"rating":null,"image_url":"43187.png","image_exist":false,"industries":"construction,interiors-real-estate-services"}],"updatedAt":"2026-03-24T17:03:47.839Z"}