{"page":1853,"total":44860,"pageSize":24,"companies":[{"slug":"josh-technology-group","name":"josh Technology Group","name_hi":null,"location":null,"rating":null,"image_url":"48447.png","image_exist":false,"industries":"other-technology-equipment-products"},{"slug":"jungleworks","name":"jungleworks","name_hi":null,"location":null,"rating":null,"image_url":"49494.png","image_exist":false,"industries":"other-services"},{"slug":"justanswer","name":"justanswer","name_hi":null,"location":null,"rating":null,"image_url":"48411.png","image_exist":false,"industries":"other-technology-equipment-products"},{"slug":"k12-techno-services-pvt-ltd","name":"k12 techno services Pvt. Ltd.","name_hi":null,"location":null,"rating":null,"image_url":"44921.png","image_exist":false,"industries":"education,training-institutes-academic-research"},{"slug":"kalycito-infotech-private-limited","name":"kalycito infotech private limited","name_hi":null,"location":null,"rating":null,"image_url":"49325.png","image_exist":false,"industries":"other-technology-services"},{"slug":"karad-projects-and-motors-limited","name":"karad projects and motors limited","name_hi":null,"location":null,"rating":null,"image_url":"49925.png","image_exist":false,"industries":"other-construction,interiors,real-estate-services"},{"slug":"kashvi-consultant","name":"kashvi consultant","name_hi":null,"location":null,"rating":null,"image_url":"48380.png","image_exist":false,"industries":"other-consultancy-services"},{"slug":"kbc-systems","name":"kbc systems","name_hi":null,"location":null,"rating":null,"image_url":"47527.png","image_exist":false,"industries":null},{"slug":"kbs-consultants","name":"kbs consultants","name_hi":null,"location":null,"rating":null,"image_url":"49812.png","image_exist":false,"industries":"other-consultancy-services"},{"slug":"ken-interactive-india-private-limited","name":"ken interactive (india) private limited","name_hi":null,"location":null,"rating":null,"image_url":"50826.png","image_exist":false,"industries":"other-education,training-institutes-academic-research"},{"slug":"kesineni-cargo-carriers-private-limited","name":"kesineni cargo carriers private limited","name_hi":null,"location":null,"rating":null,"image_url":"49358.png","image_exist":false,"industries":"other-transportation-services"},{"slug":"kgd-architecture","name":"kgd architecture","name_hi":null,"location":null,"rating":null,"image_url":"48385.png","image_exist":false,"industries":"other-construction,interiors,real-estate-services"},{"slug":"kitchen-xpress-overseas-ltd","name":"kitchen xpress overseas ltd","name_hi":null,"location":null,"rating":null,"image_url":"47208.png","image_exist":false,"industries":"other-manufacturingproduction"},{"slug":"kk-consulting-services","name":"kk consulting services","name_hi":null,"location":null,"rating":null,"image_url":"49021.png","image_exist":false,"industries":"other-consultancy-services"},{"slug":"knovos-india-pvt-ltd","name":"knovos india pvt. ltd","name_hi":null,"location":null,"rating":null,"image_url":"48720.png","image_exist":false,"industries":"other-technology-services"},{"slug":"kohinoor-planet-constructions-pvt-ltd","name":"kohinoor planet constructions pvt ltd","name_hi":null,"location":null,"rating":null,"image_url":"49748.png","image_exist":false,"industries":"other-construction,interiors,real-estate-services"},{"slug":"kpmg","name":"kpmg","name_hi":null,"location":null,"rating":null,"image_url":"48972.png","image_exist":false,"industries":"other-banking,financial-services-insurance"},{"slug":"krea-university","name":"krea university","name_hi":null,"location":null,"rating":null,"image_url":"51496.png","image_exist":false,"industries":"other-education,training-institutes-academic-research"},{"slug":"krishirasayan","name":"krishirasayan","name_hi":null,"location":null,"rating":null,"image_url":"49158.png","image_exist":false,"industries":"other-consultancy-services"},{"slug":"krishnae-infrastructure-pvt-ltd","name":"krishnae infrastructure pvt.ltd.","name_hi":null,"location":null,"rating":null,"image_url":"47403.png","image_exist":false,"industries":"other-construction,interiors,real-estate-services"},{"slug":"landbase-consulting-pvt-ltd","name":"landbase consulting pvt ltd.","name_hi":null,"location":null,"rating":null,"image_url":"46081.png","image_exist":false,"industries":"other-consultancy-services"},{"slug":"landmark-insurance-brokers-pvt-ltd","name":"landmark insurance brokers pvt ltd","name_hi":null,"location":null,"rating":null,"image_url":"45411.png","image_exist":false,"industries":"media,entertainment,advertising-related-services"},{"slug":"lanover-solutions","name":"lanover solutions","name_hi":null,"location":null,"rating":null,"image_url":"51649.png","image_exist":false,"industries":"other-technology-services"},{"slug":"lastminute-com-group","name":"lastminute.com group","name_hi":null,"location":null,"rating":null,"image_url":"50154.png","image_exist":false,"industries":"other-services"}],"updatedAt":"2026-03-24T17:03:49.613Z"}