{"page":231,"total":44860,"pageSize":24,"companies":[{"slug":"shangri-la-hotels-and-resorts","name":"Shangri La Hotels and Resorts ","name_hi":null,"location":null,"rating":null,"image_url":"6839.png","image_exist":true,"industries":"hospitality-tourism"},{"slug":"shani-peripherals-pvt-ltd","name":"Shani Peripherals Pvt Ltd","name_hi":null,"location":null,"rating":null,"image_url":"5591.png","image_exist":true,"industries":"technology-it,telecom,semiconductors"},{"slug":"shankar-jewels-ltd","name":"Shankar Jewels Ltd ","name_hi":null,"location":null,"rating":null,"image_url":"7224.png","image_exist":true,"industries":"mining,minerals,metals"},{"slug":"shanthi-gears-ltd","name":"Shanthi Gears Ltd","name_hi":null,"location":null,"rating":null,"image_url":"2740.png","image_exist":true,"industries":"heavy-machinerycapital-goods-industrial-supplies"},{"slug":"shapoorji-pallonji-co-ltd","name":"Shapoorji Pallonji & Co Ltd ","name_hi":null,"location":null,"rating":null,"image_url":"1629.png","image_exist":true,"industries":"construction,interiors-real-estate-services"},{"slug":"sharad-constructions-pvt-ltd","name":"Sharad Constructions Pvt Ltd","name_hi":null,"location":null,"rating":null,"image_url":"4763.png","image_exist":true,"industries":"construction,interiors-real-estate-services"},{"slug":"sharda-forging-stamping-pvt-ltd","name":"Sharda Forging & Stamping Pvt Ltd","name_hi":null,"location":null,"rating":null,"image_url":"5274.png","image_exist":true,"industries":"heavy-machinerycapital-goods-industrial-supplies"},{"slug":"sharda-motor-industries-ltd","name":"Sharda Motor industries Ltd ","name_hi":null,"location":null,"rating":null,"image_url":"1628.png","image_exist":true,"industries":"transportation-equipment"},{"slug":"sharda-university","name":"Sharda University","name_hi":null,"location":null,"rating":null,"image_url":"3286.png","image_exist":true,"industries":"education,training-institutes-academic-research"},{"slug":"share-microfin-ltd","name":"Share Microfin Ltd ","name_hi":null,"location":null,"rating":null,"image_url":"1626.png","image_exist":true,"industries":"banking,financial-services-insurance"},{"slug":"sharekhan-ltd","name":"Sharekhan Ltd","name_hi":null,"location":null,"rating":null,"image_url":"1627.png","image_exist":true,"industries":"banking,financial-services-insurance"},{"slug":"sharma-fabricators-erectors-pvt-ltd","name":"Sharma Fabricators & Erectors Pvt Ltd","name_hi":null,"location":null,"rating":null,"image_url":"4373.png","image_exist":true,"industries":"construction,interiors-real-estate-services"},{"slug":"sharp-india-ltd","name":"Sharp India Ltd ","name_hi":null,"location":null,"rating":null,"image_url":"1759.png","image_exist":true,"industries":"consumer-goods-durables"},{"slug":"shasun-chemicals-and-drugs-ltd","name":"Shasun Chemicals and Drugs Ltd ","name_hi":null,"location":null,"rating":null,"image_url":"1625.png","image_exist":true,"industries":"healthcare"},{"slug":"shaw-stone-webster-asia-inc","name":"Shaw Stone Webster Asia Inc ","name_hi":null,"location":null,"rating":null,"image_url":"7256.png","image_exist":true,"industries":"utilities"},{"slug":"shawman-software-pvt-ltd","name":"ShawMan Software Pvt Ltd ","name_hi":null,"location":null,"rating":null,"image_url":"4539.png","image_exist":true,"industries":"technology-it,telecom,dot-com-etc"},{"slug":"sheela-foam-pvt-ltd","name":"Sheela Foam Pvt Ltd ","name_hi":null,"location":null,"rating":null,"image_url":"3053.png","image_exist":true,"industries":"other-manufacturingproduction"},{"slug":"shell-pearl-ceramics-ltd","name":"Shell & Pearl Ceramics Ltd ","name_hi":null,"location":null,"rating":null,"image_url":"6034.png","image_exist":true,"industries":"cement,building-materials-construction-equipment"},{"slug":"shell-pvt-ltd","name":"Shell Pvt Ltd ","name_hi":null,"location":null,"rating":null,"image_url":"1622.png","image_exist":true,"industries":"oil,gas-power-energy"},{"slug":"shell-transource-pvt-ltd","name":"Shell Transource Pvt Ltd","name_hi":null,"location":null,"rating":null,"image_url":"1198.png","image_exist":true,"industries":"bpos,kpos,lpos,ites,transcription"},{"slug":"shelters-homes-properties-ltd","name":"Shelters Homes & Properties Ltd ","name_hi":null,"location":null,"rating":null,"image_url":"1621.png","image_exist":true,"industries":"construction,interiors-real-estate-services"},{"slug":"shemaroo-entertainment-pvt-ltd","name":"Shemaroo Entertainment Pvt Ltd ","name_hi":null,"location":null,"rating":null,"image_url":"4036.png","image_exist":true,"industries":"media,entertainment,advertising-related-services"},{"slug":"sheorey-digital-systems-ltd","name":"Sheorey Digital Systems Ltd","name_hi":null,"location":null,"rating":null,"image_url":"5373.png","image_exist":true,"industries":"technology-it,telecom,dot-com-etc"},{"slug":"sheth-developers-pvt-ltd","name":"Sheth Developers Pvt Ltd ","name_hi":null,"location":null,"rating":null,"image_url":"4540.png","image_exist":true,"industries":"construction,interiors-real-estate-services"}],"updatedAt":"2026-03-24T17:02:53.423Z"}