{"page":279,"total":44860,"pageSize":24,"companies":[{"slug":"viacom-18-media-pvt-ltd","name":"Viacom 18 Media Pvt Ltd ","name_hi":null,"location":null,"rating":null,"image_url":"6354.png","image_exist":true,"industries":"media,entertainment,advertising-related-services"},{"slug":"vibgyor-allied-infrastructure-ltd","name":"Vibgyor Allied Infrastructure Ltd ","name_hi":null,"location":null,"rating":null,"image_url":"5428.png","image_exist":true,"industries":"construction,interiors-real-estate-services"},{"slug":"vibha-agrotech-ltd","name":"Vibha Agrotech Ltd ","name_hi":null,"location":null,"rating":null,"image_url":"2498.png","image_exist":true,"industries":"agriculture,dairy,agro-based-industries,fishing,forestry"},{"slug":"viceroy-hotels-ltd","name":"Viceroy Hotels Ltd ","name_hi":null,"location":null,"rating":null,"image_url":"6523.png","image_exist":true,"industries":"hospitality-tourism"},{"slug":"vichi-agro-products-pvt-ltd","name":"Vichi Agro Products Pvt Ltd ","name_hi":null,"location":null,"rating":null,"image_url":"2455.png","image_exist":true,"industries":"agriculture,dairy,agro-based-industries,fishing,forestry"},{"slug":"victora-tools-engineers-pvt-ltd","name":"Victora Tools Engineers Pvt Ltd ","name_hi":null,"location":null,"rating":null,"image_url":"6522.png","image_exist":true,"industries":"heavy-machinerycapital-goods-industrial-supplies"},{"slug":"victorinox-india-pvt-ltd","name":"Victorinox India Pvt Ltd","name_hi":null,"location":null,"rating":null,"image_url":"4547.png","image_exist":true,"industries":"consumer-goods-other"},{"slug":"victory-electricals-ltd","name":"Victory Electricals Ltd ","name_hi":null,"location":null,"rating":null,"image_url":"6521.png","image_exist":true,"industries":"heavy-machinerycapital-goods-industrial-supplies"},{"slug":"videocon-industries-ltd","name":"Videocon Industries Ltd","name_hi":null,"location":null,"rating":null,"image_url":"790.png","image_exist":true,"industries":"other-industry"},{"slug":"videocon-telecommunications-ltd","name":"Videocon Telecommunications Ltd ","name_hi":null,"location":null,"rating":null,"image_url":"3064.png","image_exist":true,"industries":"technology-it,telecom,dot-com-etc"},{"slug":"videojet-technologies-india-pvt-ltd","name":"Videojet Technologies India Pvt Ltd ","name_hi":null,"location":null,"rating":null,"image_url":"6520.png","image_exist":true,"industries":"technology-it,telecom,semiconductors"},{"slug":"vidhan-enterprises","name":"Vidhan Enterprises ","name_hi":null,"location":null,"rating":null,"image_url":"6519.png","image_exist":true,"industries":"heavy-machinerycapital-goods-industrial-supplies"},{"slug":"vidushi-infotech-ssp-pvt-ltd","name":"Vidushi Infotech SSP Pvt. Ltd.","name_hi":null,"location":null,"rating":null,"image_url":"29709.png","image_exist":true,"industries":"technology-it,telecom,dot-com-etc"},{"slug":"vidyatech-solutions-pvt-ltd","name":"Vidyatech Solutions Pvt Ltd","name_hi":null,"location":null,"rating":null,"image_url":"6870.png","image_exist":true,"industries":"technology-it,telecom,dot-com-etc"},{"slug":"vidyut-control-systems-private-limited","name":"Vidyut Control Systems Private Limited","name_hi":null,"location":null,"rating":null,"image_url":"1688.png","image_exist":true,"industries":"other-services"},{"slug":"vidyut-metallics-pvt-ltd","name":"Vidyut Metallics Pvt Ltd","name_hi":null,"location":null,"rating":null,"image_url":"6149.png","image_exist":true,"industries":"consumer-goods-fmcg"},{"slug":"vignani-technologies-pvt-ltd","name":"Vignani Technologies Pvt Ltd ","name_hi":null,"location":null,"rating":null,"image_url":"2265.png","image_exist":true,"industries":"technology-it,telecom,dot-com-etc"},{"slug":"vigneshwara-exports-ltd","name":"Vigneshwara Exports Ltd","name_hi":null,"location":null,"rating":null,"image_url":"6150.png","image_exist":true,"industries":"exporters,importers"},{"slug":"vihaan-networks-ltd","name":"Vihaan Networks Ltd ","name_hi":null,"location":null,"rating":null,"image_url":"3065.png","image_exist":true,"industries":null},{"slug":"vij-engineers-consultants-pvt-ltd","name":"Vij Engineers & Consultants Pvt Ltd ","name_hi":null,"location":null,"rating":null,"image_url":"4131.png","image_exist":true,"industries":"mining,minerals,metals"},{"slug":"vijai-electricals-ltd","name":"Vijai Electricals Ltd ","name_hi":null,"location":null,"rating":null,"image_url":"3390.png","image_exist":true,"industries":"heavy-machinerycapital-goods-industrial-supplies"},{"slug":"vijay-computers","name":"Vijay Computers ","name_hi":null,"location":null,"rating":null,"image_url":"6517.png","image_exist":true,"industries":"retail,shops,malls"},{"slug":"vijay-dairy-farm-products-pvt-ltd","name":"Vijay Dairy & Farm Products Pvt Ltd","name_hi":null,"location":null,"rating":null,"image_url":"4618.png","image_exist":true,"industries":"agriculture,dairy,agro-based-industries,fishing,forestry"},{"slug":"vijay-nirman-company-pvt-ltd","name":"Vijay Nirman Company Pvt Ltd ","name_hi":null,"location":null,"rating":null,"image_url":"3953.png","image_exist":true,"industries":"construction,interiors-real-estate-services"}],"updatedAt":"2026-03-24T17:02:54.825Z"}