{"page":66,"total":44860,"pageSize":24,"companies":[{"slug":"consolidated-contractors-co","name":"Consolidated Contractors Co","name_hi":null,"location":null,"rating":null,"image_url":"224.png","image_exist":true,"industries":"construction,interiors-real-estate-services"},{"slug":"consolidated-hoists-pvt-ltd","name":"Consolidated Hoists Pvt Ltd","name_hi":null,"location":null,"rating":null,"image_url":"7087.png","image_exist":true,"industries":"heavy-machinerycapital-goods-industrial-supplies"},{"slug":"consulting-engineers-group-ltd","name":"Consulting Engineers Group Ltd ","name_hi":null,"location":null,"rating":null,"image_url":"3480.png","image_exist":true,"industries":"construction,interiors-real-estate-services"},{"slug":"continental-automotive-components-india-pvt-ltd","name":"Continental Automotive Components India Pvt Ltd","name_hi":null,"location":null,"rating":null,"image_url":"5382.png","image_exist":true,"industries":"heavy-machinerycapital-goods-industrial-supplies"},{"slug":"continental-controls-ltd","name":"Continental Controls Ltd ","name_hi":null,"location":null,"rating":null,"image_url":"3791.png","image_exist":true,"industries":"heavy-machinerycapital-goods-industrial-supplies"},{"slug":"continental-device-india-ltd","name":"Continental Device India Ltd ","name_hi":null,"location":null,"rating":null,"image_url":"4209.png","image_exist":true,"industries":"technology-it,telecom,semiconductors"},{"slug":"continental-engineering-corporation-india-pvt-ltd","name":"Continental Engineering Corporation India Pvt Ltd ","name_hi":null,"location":null,"rating":null,"image_url":"4267.png","image_exist":true,"industries":"infrastructure-development-airports,ports,sezs,roads,rail-etc"},{"slug":"continental-engines-ltd","name":"Continental Engines Ltd","name_hi":null,"location":null,"rating":null,"image_url":"5546.png","image_exist":true,"industries":"heavy-machinerycapital-goods-industrial-supplies"},{"slug":"continuserve-softech-india-pvt-ltd","name":"Continuserve Softech India Pvt Ltd ","name_hi":null,"location":null,"rating":null,"image_url":"8305.png","image_exist":true,"industries":"technology-it,telecom,dot-com-etc"},{"slug":"contract-advertising-india-ltd","name":"Contract Advertising India Ltd ","name_hi":null,"location":null,"rating":null,"image_url":"3715.png","image_exist":true,"industries":"media,entertainment,advertising-related-services"},{"slug":"control-print-ltd","name":"Control Print Ltd","name_hi":null,"location":null,"rating":null,"image_url":"2895.png","image_exist":true,"industries":"other-manufacturingproduction"},{"slug":"convergys-india-pvt-ltd","name":"Convergys India Pvt Ltd ","name_hi":null,"location":null,"rating":null,"image_url":"35.png","image_exist":true,"industries":"bpos,kpos,lpos,ites,transcription"},{"slug":"converse-inc","name":"Converse Inc","name_hi":null,"location":null,"rating":null,"image_url":"3281.png","image_exist":true,"industries":"consumer-goods-other"},{"slug":"cook-india-medical-devices-pvt-ltd","name":"Cook India Medical Devices Pvt Ltd","name_hi":null,"location":null,"rating":null,"image_url":"3792.png","image_exist":true,"industries":"healthcare"},{"slug":"cooper-bussmann-india-pvt-ltd","name":"Cooper Bussmann India Pvt Ltd","name_hi":null,"location":null,"rating":null,"image_url":"7252.png","image_exist":true,"industries":"technology-it,telecom,semiconductors"},{"slug":"cooper-pharma-ltd","name":"Cooper Pharma Ltd ","name_hi":null,"location":null,"rating":null,"image_url":"3793.png","image_exist":true,"industries":"healthcare"},{"slug":"copal-research-india-pvt-ltd","name":"Copal Research India Pvt Ltd","name_hi":null,"location":null,"rating":null,"image_url":"2301.png","image_exist":true,"industries":"bpos,kpos,lpos,ites,transcription"},{"slug":"corbus-india-pvt-ltd","name":"Corbus India Pvt Ltd","name_hi":null,"location":null,"rating":null,"image_url":"1178.png","image_exist":true,"industries":"technology-it,telecom,dot-com-etc"},{"slug":"cords-cable-industries-ltd","name":"Cords Cable Industries Ltd","name_hi":null,"location":null,"rating":null,"image_url":"2757.png","image_exist":true,"industries":"heavy-machinerycapital-goods-industrial-supplies"},{"slug":"core-chemicals-pvt-ltd","name":"Core Chemicals Pvt Ltd ","name_hi":null,"location":null,"rating":null,"image_url":"3837.png","image_exist":true,"industries":"chemicals,paints-fertilizers"},{"slug":"coromandel-international-ltd","name":"Coromandel International Ltd ","name_hi":null,"location":null,"rating":null,"image_url":"2435.png","image_exist":true,"industries":"chemicals,paints-fertilizers"},{"slug":"corona-bus-manufacturers-pvt-ltd","name":"Corona Bus Manufacturers Pvt Ltd","name_hi":null,"location":null,"rating":null,"image_url":"4731.png","image_exist":true,"industries":"transportation-equipment"},{"slug":"corporate-zoom-people-solutions","name":"Corporate Zoom People Solutions","name_hi":null,"location":null,"rating":null,"image_url":"45271.png","image_exist":true,"industries":"consultancy-services"},{"slug":"corporateserve-solutions-pvt-ltd","name":"CorporateServe Solutions Pvt Ltd ","name_hi":null,"location":null,"rating":null,"image_url":"7187.png","image_exist":true,"industries":"technology-it,telecom,dot-com-etc"}],"updatedAt":"2026-03-24T17:02:48.533Z"}